{"cple6.pdf": {"Dados da Companhia": {"csv": {"Nome de Preg\u00e3o:": "COPEL", "C\u00f3digos de Negocia\u00e7\u00e3o:": "Mais C\u00f3digos\nCPLE3; CPLE5; CPLE6", "CNPJ:": "76.483.817/0001-20", "Atividade Principal:": "Gera\u00e7\u00e3o. Transmiss\u00e3o. Comercializa\u00e7\u00e3o E\nDistribui\u00e7\u00e3o de Energia El\u00e9trica", "Classi\u0000ca\u00e7\u00e3o Setorial:": "Utilidade P\u00fablica / Energia El\u00e9trica /\nEnergia El\u00e9trica", "Site:": "http://ri.copel.com (http://http://ri.copel.com)"}}, "Dados Econ\u00f4mico-Financeiros - R$ - mil": {"Balan\u00e7o Patrimonial - Consolidado": {"csv": {"Ativo Imobilizado, Investimentos e Intang\u00edvel - Inicial": "23.672.926", "Ativo Imobilizado, Investimentos e Intang\u00edvel - Final": "25.507.307", "Ativo Total - Inicial": "49.703.700", "Ativo Total - Final": "55.819.074", "Patrim\u00f4nio L\u00edquido - Inicial": "21.131.225", "Patrim\u00f4nio L\u00edquido - Final": "24.191.667", "Patrim\u00f4nio L\u00edquido Atribu\u00eddo \u00e0 Controladora - Inicial": "20.817.364", "Patrim\u00f4nio L\u00edquido Atribu\u00eddo \u00e0 Controladora - Final": "23.886.153"}, "Inicio": "31/12/2022", "Fim": "31/12/2023"}, "Demonstra\u00e7\u00e3o do Resultado - Consolidado": {"csv": {"Receita de Venda - Inicial": "20.535.341", "Receita de Venda - Final": "21.479.468", "Resultado Bruto - Inicial": "4.929.757", "Resultado Bruto - Final": "4.898.040", "Resultado de Equival\u00eancia Patrimonial - Inicial": "478.577", "Resultado de Equival\u00eancia Patrimonial - Final": "307.809", "Resultado Financeiro - Inicial": "(2.005.884)", "Resultado Financeiro - Final": "(1.204.990)", "Resultado L\u00edquido das Opera\u00e7\u00f5es Continuadas - Inicial": "1.223.987", "Resultado L\u00edquido das Opera\u00e7\u00f5es Continuadas - Final": "2.135.667", "Lucro (Preju\u00edzo) do Per\u00edodo - Inicial": "1.149.321", "Lucro (Preju\u00edzo) do Per\u00edodo - Final": "2.327.168", "Lucro (Preju\u00edzo) do Per\u00edodo Atribu\u00eddo \u00e0 Controladora - Inicial": "1.112.007", "Lucro (Preju\u00edzo) do Per\u00edodo Atribu\u00eddo \u00e0 Controladora - Final": "2.258.810"}, "Inicio": "01/01/2022 a\n31/12/2022", "Fim": "01/01/2023 a\n31/12/2023"}, "Demonstra\u00e7\u00e3o do Fluxo de Caixa - Consolidado": {"csv": {"Atividades Operacionais - Inicial": "3.902.649", "Atividades Operacionais - Final": "3.518.476", "Atividades de Investimento - Inicial": "(2.774.996)", "Atividades de Investimento - Final": "(3.135.091)", "Demonstra\u00e7\u00e3o do Fluxo de Caixa - Inicial": "Consolidado", "Demonstra\u00e7\u00e3o do Fluxo de Caixa - Final": "-", "Atividades de Financiamento - Inicial": "(1.922.041)", "Atividades de Financiamento - Final": "2.696.572", "Varia\u00e7\u00e3o Cambial sobre Caixa e Equivalentes - Inicial": "0", "Varia\u00e7\u00e3o Cambial sobre Caixa e Equivalentes - Final": "0", "Aumento (Redu\u00e7\u00e3o) de Caixa e Equivalentes - Inicial": "(794.388)", "Aumento (Redu\u00e7\u00e3o) de Caixa e Equivalentes - Final": "3.079.957"}, "Inicio": "01/01/2022 a\n31/12/2022", "Fim": "01/01/2023 a\n31/12/2023"}}, "Posi\u00e7\u00e3o Acion\u00e1ria*": {"Bndes Participa\u00e7\u00f5es S.A. - Bndespar %ON": "10,09", "Bndes Participa\u00e7\u00f5es S.A. - Bndespar %PN": "31,18", "Bndes Participa\u00e7\u00f5es S.A. - Bndespar %TOTAL": "21,99", "Estado Do Paran\u00e1 %ON": "27,57", "Estado Do Paran\u00e1 %PN": "6,90", "Estado Do Paran\u00e1 %TOTAL": "15,91", "Gqg Partners Llc. %ON": "4,53", "Gqg Partners Llc. %PN": "0,00", "Gqg Partners Llc. %TOTAL": "1,97", "Radar Gestora de Recursos Ltda %ON": "0,00", "Radar Gestora de Recursos Ltda %PN": "5,93", "Radar Gestora de Recursos Ltda %TOTAL": "3,35", "Victor Adler %ON": "0,31", "Victor Adler %PN": "0,27", "Victor Adler %TOTAL": "0,28", "Outros %ON": "57,50", "Outros %PN": "55,72", "Outros %TOTAL": "56,50", "A\u00e7\u00f5es Tesouraria %ON": "0,00", "A\u00e7\u00f5es Tesouraria %PN": "0,00", "A\u00e7\u00f5es Tesouraria %TOTAL": "0,00"}, "A\u00e7\u00f5es em Circula\u00e7\u00e3o no Mercado": {"date": "29/04/2022", "csv": {"Pessoas F\u00edsicas - Quantidade": "262.684", "Pessoas F\u00edsicas - Percentual": "-", "Pessoas Jur\u00eddicas - Quantidade": "950", "Pessoas Jur\u00eddicas - Percentual": "-", "Investidores Institucionais - Quantidade": "1.075", "Investidores Institucionais - Percentual": "-", "Quantidade de A\u00e7\u00f5es Ordin\u00e1rias - Quantidade": "319.774.264", "Quantidade de A\u00e7\u00f5es Ordin\u00e1rias - Percentual": "30,34", "Quantidade de A\u00e7\u00f5es Preferenciais - Quantidade": "1.566.493.506", "Quantidade de A\u00e7\u00f5es Preferenciais - Percentual": "93,11", "Total de A\u00e7\u00f5es - Quantidade": "1.886.267.770", "Total de A\u00e7\u00f5es - Percentual": "68,93"}}, "Composi\u00e7\u00e3o do Capital Social": {"date": "06/09/2023", "csv": {"Ordin\u00e1rias": "1.300.347.300", "Preferenciais": "1.682.463.291", "Total": "2.982.810.591"}}}, "bbas3.pdf": {"Dados da Companhia": {"csv": {"Nome de Preg\u00e3o:": "BRASIL", "C\u00f3digos de Negocia\u00e7\u00e3o:": "Mais C\u00f3digos\nBBAS11; BBAS12; BBAS3", "CNPJ:": "00.000.000/0001-91", "Atividade Principal:": "Banco M\u00faltiplo", "Classi\u0000ca\u00e7\u00e3o Setorial:": "Financeiro / Intermedi\u00e1rios Financeiros /\nBancos", "Site:": "www.bb.com.br (http://www.bb.com.br)"}}, "Dados Econ\u00f4mico-Financeiros - R$ - mil": {"Balan\u00e7o Patrimonial - Consolidado": {"csv": {"Ativo Imobilizado, Investimentos e Intang\u00edvel - Inicial": "24.231.113", "Ativo Imobilizado, Investimentos e Intang\u00edvel - Final": "24.919.935", "Ativo Total - Inicial": "2.008.168.606", "Ativo Total - Final": "2.153.878.452", "Patrim\u00f4nio L\u00edquido - Inicial": "153.839.319", "Patrim\u00f4nio L\u00edquido - Final": "163.638.226"}, "Inicio": "31/12/2022", "Fim": "31/12/2023"}, "Demonstra\u00e7\u00e3o do Resultado - Consolidado": {"csv": {"Receita da Intermedia\u00e7\u00e3o Financeira - Inicial": "236.549.051", "Receita da Intermedia\u00e7\u00e3o Financeira - Final": "265.438.605", "Resultado Bruto da Intermedia\u00e7\u00e3o Financeira - Inicial": "74.346.567", "Resultado Bruto da Intermedia\u00e7\u00e3o Financeira - Final": "88.748.731", "Resultado de Equival\u00eancia Patrimonial - Inicial": "(20.959.329)", "Resultado de Equival\u00eancia Patrimonial - Final": "(23.626.688)", "Lucro (Preju\u00edzo) do Per\u00edodo - Inicial": "30.897.625", "Lucro (Preju\u00edzo) do Per\u00edodo - Final": "33.614.852"}, "Inicio": "01/01/2022 a\n31/12/2022", "Fim": "01/01/2023 a\n31/12/2023"}, "Demonstra\u00e7\u00e3o do Fluxo de Caixa - Consolidado": {"csv": {"Atividades Operacionais - Inicial": "66.057.337", "Atividades Operacionais - Final": "14.740.786", "Atividades de Investimento - Inicial": "(18.010.230)", "Atividades de Investimento - Final": "21.641.070", "Atividades de Financiamento - Inicial": "(28.214.362)", "Atividades de Financiamento - Final": "(34.341.950)", "Varia\u00e7\u00e3o Cambial sobre Caixa e Equivalentes - Inicial": "(5.501.147)", "Varia\u00e7\u00e3o Cambial sobre Caixa e Equivalentes - Final": "(15.866.370)", "Aumento (Redu\u00e7\u00e3o) de Caixa e Equivalentes - Inicial": "14.331.598", "Aumento (Redu\u00e7\u00e3o) de Caixa e Equivalentes - Final": "(13.826.464)"}, "Inicio": "01/01/2022 a\n31/12/2022", "Fim": "01/01/2023 a\n31/12/2023"}}, "Posi\u00e7\u00e3o Acion\u00e1ria*": {"Minist\u00e9rio Da Economia / Secretaria Do Tesouro Nacional %ON": "50,00", "Minist\u00e9rio Da Economia / Secretaria Do Tesouro Nacional %PN": "0,00", "Minist\u00e9rio Da Economia / Secretaria Do Tesouro Nacional %TOTAL": "50,00", "Outros %ON": "49,60", "Outros %PN": "0,00", "Outros %TOTAL": "49,60", "A\u00e7\u00f5es Tesouraria %ON": "0,41", "A\u00e7\u00f5es Tesouraria %PN": "0,00", "A\u00e7\u00f5es Tesouraria %TOTAL": "0,41"}, "A\u00e7\u00f5es em Circula\u00e7\u00e3o no Mercado": {"date": "27/04/2022", "csv": {"Pessoas F\u00edsicas - Quantidade": "853.913", "Pessoas F\u00edsicas - Percentual": "-", "Pessoas Jur\u00eddicas - Quantidade": "15.061", "Pessoas Jur\u00eddicas - Percentual": "-", "Investidores Institucionais - Quantidade": "1.438", "Investidores Institucionais - Percentual": "-", "Quantidade de A\u00e7\u00f5es Ordin\u00e1rias - Quantidade": "1.420.731.069", "Quantidade de A\u00e7\u00f5es Ordin\u00e1rias - Percentual": "49,58", "Total de A\u00e7\u00f5es - Quantidade": "1.420.731.069", "Total de A\u00e7\u00f5es - Percentual": "49,58"}}, "Composi\u00e7\u00e3o do Capital Social": {"date": "28/04/2023", "csv": {"Ordin\u00e1rias": "2.865.417.020", "Preferenciais": "0", "Total": "2.865.417.020"}}}, "petz3.pdf": {"Dados da Companhia": {"csv": {"Nome de Preg\u00e3o:": "PETZ", "C\u00f3digos de Negocia\u00e7\u00e3o:": "Mais C\u00f3digos\nPETZ3", "CNPJ:": "18.328.118/0001-09", "Atividade Principal:": "Importa\u00e7\u00e3o. Exporta\u00e7\u00e3o E Com\u00e9rcio\n(inclusive Via Internet E-commerce) de\nArtigos Para Animais. Plantas. Flores.\nSementes; Hospital Veterin\u00e1rio. Consult\u00f3rio.\nCl\u00ednica Veterin\u00e1ria. Banho/tosa E Hotel.", "Classi\u0000ca\u00e7\u00e3o Setorial:": "Consumo C\u00edclico / Com\u00e9rcio / Produtos\nDiversos", "Site:": "www.petz.com.br (http://www.petz.com.br)"}}, "Dados Econ\u00f4mico-Financeiros - R$ - mil": {"Balan\u00e7o Patrimonial - Consolidado": {"csv": {"Ativo Imobilizado, Investimentos e Intang\u00edvel - Inicial": "2.449.887", "Ativo Imobilizado, Investimentos e Intang\u00edvel - Final": "2.465.776", "Ativo Total - Inicial": "3.647.129", "Ativo Total - Final": "3.995.411", "Patrim\u00f4nio L\u00edquido - Inicial": "1.840.572", "Patrim\u00f4nio L\u00edquido - Final": "1.808.893", "Patrim\u00f4nio L\u00edquido Atribu\u00eddo \u00e0 Controladora - Inicial": "1.840.572", "Patrim\u00f4nio L\u00edquido Atribu\u00eddo \u00e0 Controladora - Final": "1.808.893"}, "Inicio": "31/12/2022", "Fim": "31/12/2023"}, "Demonstra\u00e7\u00e3o do Resultado - Consolidado": {"csv": {"Receita de Venda - Inicial": "2.834.533", "Receita de Venda - Final": "3.173.241", "Resultado Bruto - Inicial": "1.350.572", "Resultado Bruto - Final": "1.481.788", "Resultado de Equival\u00eancia Patrimonial - Inicial": "0", "Resultado de Equival\u00eancia Patrimonial - Final": "0", "Resultado Financeiro - Inicial": "(61.231)", "Resultado Financeiro - Final": "(101.578)", "Resultado L\u00edquido das Opera\u00e7\u00f5es Continuadas - Inicial": "50.590", "Resultado L\u00edquido das Opera\u00e7\u00f5es Continuadas - Final": "16.349", "Lucro (Preju\u00edzo) do Per\u00edodo - Inicial": "50.590", "Lucro (Preju\u00edzo) do Per\u00edodo - Final": "16.349", "Lucro (Preju\u00edzo) do Per\u00edodo Atribu\u00eddo \u00e0 Controladora - Inicial": "0", "Lucro (Preju\u00edzo) do Per\u00edodo Atribu\u00eddo \u00e0 Controladora - Final": "0"}, "Inicio": "01/01/2022 a\n31/12/2022", "Fim": "01/01/2023 a\n31/12/2023"}, "Demonstra\u00e7\u00e3o do Fluxo de Caixa - Consolidado": {"csv": {"Atividades Operacionais - Inicial": "202.790", "Atividades Operacionais - Final": "429.095", "Atividades de Investimento - Inicial": "(396.406)", "Atividades de Investimento - Final": "(616.532)", "Atividades de Financiamento - Inicial": "(294.645)", "Atividades de Financiamento - Final": "120.319", "Varia\u00e7\u00e3o Cambial sobre Caixa e Equivalentes - Inicial": "0", "Varia\u00e7\u00e3o Cambial sobre Caixa e Equivalentes - Final": "(62.068)", "Demonstra\u00e7\u00e3o do Fluxo de Caixa - Inicial": "Consolidado", "Demonstra\u00e7\u00e3o do Fluxo de Caixa - Final": "-", "Aumento (Redu\u00e7\u00e3o) de Caixa e Equivalentes - Inicial": "(488.261)", "Aumento (Redu\u00e7\u00e3o) de Caixa e Equivalentes - Final": "(129.186)"}, "Inicio": "01/01/2022 a\n31/12/2022", "Fim": "01/01/2023 a\n31/12/2023"}}, "Posi\u00e7\u00e3o Acion\u00e1ria*": {"Atmos Capital Gestao de Recursos Ltda %ON": "5,45", "Atmos Capital Gestao de Recursos Ltda %PN": "0,00", "Atmos Capital Gestao de Recursos Ltda %TOTAL": "5,45", "Platina 55 Fim %ON": "2,59", "Platina 55 Fim %PN": "0,00", "Platina 55 Fim %TOTAL": "2,59", "Sergio Zimerman %ON": "26,47", "Sergio Zimerman %PN": "0,00", "Sergio Zimerman %TOTAL": "26,47", "Xp Investimentos Corretora de C\u00e2mbio. T\u00edtulos E Valores %ON": "Mobili\u00e1rios\n8,42", "Xp Investimentos Corretora de C\u00e2mbio. T\u00edtulos E Valores %PN": "0,00", "Xp Investimentos Corretora de C\u00e2mbio. T\u00edtulos E Valores %TOTAL": "8,42\nS.A.", "Outros %ON": "54,56", "Outros %PN": "0,00", "Outros %TOTAL": "54,56", "A\u00e7\u00f5es Tesouraria %ON": "2,51", "A\u00e7\u00f5es Tesouraria %PN": "0,00", "A\u00e7\u00f5es Tesouraria %TOTAL": "2,51"}, "A\u00e7\u00f5es em Circula\u00e7\u00e3o no Mercado": {"date": "26/04/2022", "csv": {"Pessoas F\u00edsicas - Quantidade": "93.903", "Pessoas F\u00edsicas - Percentual": "-", "Pessoas Jur\u00eddicas - Quantidade": "282", "Pessoas Jur\u00eddicas - Percentual": "-", "Investidores Institucionais - Quantidade": "1.146", "Investidores Institucionais - Percentual": "-", "Quantidade de A\u00e7\u00f5es Ordin\u00e1rias - Quantidade": "335.865.260", "Quantidade de A\u00e7\u00f5es Ordin\u00e1rias - Percentual": "72,62", "Total de A\u00e7\u00f5es - Quantidade": "335.865.260", "Total de A\u00e7\u00f5es - Percentual": "72,62"}}, "Composi\u00e7\u00e3o do Capital Social": {"date": "31/08/2023", "csv": {"Ordin\u00e1rias": "462.523.502", "Preferenciais": "0", "Total": "462.523.502"}}}, "taee11.pdf": {"Dados da Companhia": {"csv": {"Nome de Preg\u00e3o:": "TAESA", "C\u00f3digos de Negocia\u00e7\u00e3o:": "Mais C\u00f3digos\nTAEE11; TAEE3; TAEE4", "CNPJ:": "07.859.971/0001-30", "Atividade Principal:": "Transmiss\u00e3o de Energia El\u00e9trica.", "Classi\u0000ca\u00e7\u00e3o Setorial:": "Utilidade P\u00fablica / Energia El\u00e9trica /\nEnergia El\u00e9trica", "Site:": "www.taesa.com.br\n(http://www.taesa.com.br)"}}, "Dados Econ\u00f4mico-Financeiros - R$ - mil": {"Balan\u00e7o Patrimonial - Consolidado": {"csv": {"Ativo Imobilizado, Investimentos e Intang\u00edvel - Inicial": "3.951.961", "Ativo Imobilizado, Investimentos e Intang\u00edvel - Final": "3.889.620", "Ativo Total - Inicial": "17.309.081", "Ativo Total - Final": "19.448.656", "Patrim\u00f4nio L\u00edquido - Inicial": "6.570.476", "Patrim\u00f4nio L\u00edquido - Final": "6.679.310", "Patrim\u00f4nio L\u00edquido Atribu\u00eddo \u00e0 Controladora - Inicial": "6.570.476", "Patrim\u00f4nio L\u00edquido Atribu\u00eddo \u00e0 Controladora - Final": "6.679.310"}, "Inicio": "31/12/2022", "Fim": "31/12/2023"}, "Demonstra\u00e7\u00e3o do Resultado - Consolidado": {"csv": {"Receita de Venda - Inicial": "2.616.517", "Receita de Venda - Final": "3.362.116", "Resultado Bruto - Inicial": "2.118.069", "Resultado Bruto - Final": "2.121.396", "Resultado de Equival\u00eancia Patrimonial - Inicial": "564.887", "Resultado de Equival\u00eancia Patrimonial - Final": "427.513", "Resultado Financeiro - Inicial": "(737.557)", "Resultado Financeiro - Final": "(903.822)", "Resultado L\u00edquido das Opera\u00e7\u00f5es Continuadas - Inicial": "1.449.215", "Resultado L\u00edquido das Opera\u00e7\u00f5es Continuadas - Final": "1.367.834", "Lucro (Preju\u00edzo) do Per\u00edodo - Inicial": "1.449.215", "Lucro (Preju\u00edzo) do Per\u00edodo - Final": "1.367.834", "Lucro (Preju\u00edzo) do Per\u00edodo Atribu\u00eddo \u00e0 Controladora - Inicial": "1.449.215", "Lucro (Preju\u00edzo) do Per\u00edodo Atribu\u00eddo \u00e0 Controladora - Final": "1.367.834"}, "Inicio": "01/01/2022 a\n31/12/2022", "Fim": "01/01/2023 a\n31/12/2023"}, "Demonstra\u00e7\u00e3o do Fluxo de Caixa - Consolidado": {"csv": {"Atividades Operacionais - Inicial": "2.010.871", "Atividades Operacionais - Final": "756.402", "Atividades de Investimento - Inicial": "(311.208)", "Atividades de Investimento - Final": "(75.297)", "Demonstra\u00e7\u00e3o do Fluxo de Caixa - Inicial": "Consolidado", "Demonstra\u00e7\u00e3o do Fluxo de Caixa - Final": "-", "Atividades de Financiamento - Inicial": "(1.001.313)", "Atividades de Financiamento - Final": "(458.158)", "Varia\u00e7\u00e3o Cambial sobre Caixa e Equivalentes - Inicial": "0", "Varia\u00e7\u00e3o Cambial sobre Caixa e Equivalentes - Final": "0", "Aumento (Redu\u00e7\u00e3o) de Caixa e Equivalentes - Inicial": "698.350", "Aumento (Redu\u00e7\u00e3o) de Caixa e Equivalentes - Final": "222.947"}, "Inicio": "01/01/2022 a\n31/12/2022", "Fim": "01/01/2023 a\n31/12/2023"}}, "Posi\u00e7\u00e3o Acion\u00e1ria*": {"Blackrock. Inc. %ON": "0,00", "Blackrock. Inc. %PN": "5,18", "Blackrock. Inc. %TOTAL": "2,22", "Companhia Energ\u00e9tica de Minas Gerais %ON": "36,97", "Companhia Energ\u00e9tica de Minas Gerais %PN": "1,28", "Companhia Energ\u00e9tica de Minas Gerais %TOTAL": "21,68", "Isa Investimentos E Participa\u00e7\u00f5es Do Brasil S.A. %ON": "26,03", "Isa Investimentos E Participa\u00e7\u00f5es Do Brasil S.A. %PN": "0,00", "Isa Investimentos E Participa\u00e7\u00f5es Do Brasil S.A. %TOTAL": "14,88", "Outros %ON": "37,00", "Outros %PN": "93,55", "Outros %TOTAL": "61,23", "A\u00e7\u00f5es Tesouraria %ON": "0,00", "A\u00e7\u00f5es Tesouraria %PN": "0,00", "A\u00e7\u00f5es Tesouraria %TOTAL": "0,00"}, "A\u00e7\u00f5es em Circula\u00e7\u00e3o no Mercado": {"date": "29/04/2021", "csv": {"Pessoas F\u00edsicas - Quantidade": "392.926", "Pessoas F\u00edsicas - Percentual": "-", "Pessoas Jur\u00eddicas - Quantidade": "445", "Pessoas Jur\u00eddicas - Percentual": "-", "Investidores Institucionais - Quantidade": "1.175", "Investidores Institucionais - Percentual": "-", "Quantidade de A\u00e7\u00f5es Ordin\u00e1rias - Quantidade": "218.568.274", "Quantidade de A\u00e7\u00f5es Ordin\u00e1rias - Percentual": "37,00", "Quantidade de A\u00e7\u00f5es Preferenciais - Quantidade": "437.136.468", "Quantidade de A\u00e7\u00f5es Preferenciais - Percentual": "98,72", "Total de A\u00e7\u00f5es - Quantidade": "655.704.742", "Total de A\u00e7\u00f5es - Percentual": "63,45"}}, "Composi\u00e7\u00e3o do Capital Social": {"date": "29/09/2016", "csv": {"Ordin\u00e1rias": "590.714.069", "-": "29/09/2016", "Preferenciais": "442.782.652", "Total": "1.033.496.721"}}}, "igti11.pdf": {"Dados da Companhia": {"csv": {"Nome de Preg\u00e3o:": "IGUATEMI S.A", "C\u00f3digos de Negocia\u00e7\u00e3o:": "Mais C\u00f3digos\nIGTI11; IGTI3; IGTI4", "CNPJ:": "60.543.816/0001-93", "Atividade Principal:": "Explora\u00e7\u00e3o Comercial. Adminstra\u00e7\u00e3o E\nPlanejamento de Shopping Centers\n(conforme Artigo 3o. Do Estatuto Social)", "Classi\u0000ca\u00e7\u00e3o Setorial:": "Financeiro / Explora\u00e7\u00e3o de Im\u00f3veis /\nExplora\u00e7\u00e3o de Im\u00f3veis", "Site:": "ri.iguatemi.com.br\n(http://ri.iguatemi.com.br)"}}, "Dados Econ\u00f4mico-Financeiros - R$ - mil": {"Balan\u00e7o Patrimonial - Consolidado": {"csv": {"Ativo Imobilizado, Investimentos e Intang\u00edvel - Inicial": "5.493.036", "Ativo Imobilizado, Investimentos e Intang\u00edvel - Final": "5.539.905", "Ativo Total - Inicial": "8.048.137", "Ativo Total - Final": "7.791.679", "Patrim\u00f4nio L\u00edquido - Inicial": "4.107.688", "Patrim\u00f4nio L\u00edquido - Final": "4.177.518", "Patrim\u00f4nio L\u00edquido Atribu\u00eddo \u00e0 Controladora - Inicial": "4.093.329", "Patrim\u00f4nio L\u00edquido Atribu\u00eddo \u00e0 Controladora - Final": "4.177.323"}, "Inicio": "31/12/2022", "Fim": "31/12/2023"}, "Demonstra\u00e7\u00e3o do Resultado - Consolidado": {"csv": {"Receita de Venda - Inicial": "1.016.341", "Receita de Venda - Final": "1.157.163", "Resultado Bruto - Inicial": "595.457", "Resultado Bruto - Final": "738.955", "Resultado de Equival\u00eancia Patrimonial - Inicial": "(4.400)", "Resultado de Equival\u00eancia Patrimonial - Final": "(33.787)", "Resultado Financeiro - Inicial": "(625.684)", "Resultado Financeiro - Final": "(260.331)", "Resultado L\u00edquido das Opera\u00e7\u00f5es Continuadas - Inicial": "12.821", "Resultado L\u00edquido das Opera\u00e7\u00f5es Continuadas - Final": "308.934", "Lucro (Preju\u00edzo) do Per\u00edodo - Inicial": "12.821", "Lucro (Preju\u00edzo) do Per\u00edodo - Final": "308.934", "Lucro (Preju\u00edzo) do Per\u00edodo Atribu\u00eddo \u00e0 Controladora - Inicial": "7.568", "Lucro (Preju\u00edzo) do Per\u00edodo Atribu\u00eddo \u00e0 Controladora - Final": "304.713"}, "Inicio": "01/01/2022 a\n31/12/2022", "Fim": "01/01/2023 a\n31/12/2023"}, "Demonstra\u00e7\u00e3o do Fluxo de Caixa - Consolidado": {"csv": {"Atividades Operacionais - Inicial": "192.739", "Atividades Operacionais - Final": "378.103", "Atividades de Investimento - Inicial": "(410.805)", "Atividades de Investimento - Final": "(458.186)", "Atividades de Financiamento - Inicial": "231.300", "Atividades de Financiamento - Final": "87.392", "Varia\u00e7\u00e3o Cambial sobre Caixa e Equivalentes - Inicial": "0", "Varia\u00e7\u00e3o Cambial sobre Caixa e Equivalentes - Final": "0", "Aumento (Redu\u00e7\u00e3o) de Caixa e Equivalentes - Inicial": "13.234", "Aumento (Redu\u00e7\u00e3o) de Caixa e Equivalentes - Final": "7.309"}, "Inicio": "01/01/2022 a\n31/12/2022", "Fim": "01/01/2023 a\n31/12/2023"}}, "Posi\u00e7\u00e3o Acion\u00e1ria*": {"Blackrock %ON": "1,39", "Blackrock %PN": "4,99", "Blackrock %TOTAL": "2,68", "Cesena Sp Empreendimentos Imobili\u00e1rios S.A. %ON": "0,05", "Cesena Sp Empreendimentos Imobili\u00e1rios S.A. %PN": "0,00", "Cesena Sp Empreendimentos Imobili\u00e1rios S.A. %TOTAL": "0,03", "Diana Jereissati Legey %ON": "1,73", "Diana Jereissati Legey %PN": "0,00", "Diana Jereissati Legey %TOTAL": "1,11", "Gj Investimentos E Participa\u00e7\u00f5es S.A. %ON": "62,52", "Gj Investimentos E Participa\u00e7\u00f5es S.A. %PN": "1,62", "Gj Investimentos E Participa\u00e7\u00f5es S.A. %TOTAL": "40,67", "Grande Moinho Cearense S.A. %ON": "0,11", "Grande Moinho Cearense S.A. %PN": "0,00", "Grande Moinho Cearense S.A. %TOTAL": "0,07", "Kalila Representa\u00e7\u00f5es Comerciais Ltda %ON": "0,18", "Kalila Representa\u00e7\u00f5es Comerciais Ltda %PN": "0,30", "Kalila Representa\u00e7\u00f5es Comerciais Ltda %TOTAL": "0,23", "Lfj Participa\u00e7\u00f5es Ltda %ON": "0,03", "Lfj Participa\u00e7\u00f5es Ltda %PN": "0,00", "Lfj Participa\u00e7\u00f5es Ltda %TOTAL": "0,02", "Lia Ribeiro Jereissati %ON": "1,72", "Lia Ribeiro Jereissati %PN": "0,00", "Lia Ribeiro Jereissati %TOTAL": "1,11", "Mlrj Imobili\u00e1ria S.A. %ON": "0,01", "Mlrj Imobili\u00e1ria S.A. %PN": "0,00", "Mlrj Imobili\u00e1ria S.A. %TOTAL": "0,01", "Norges Bank %ON": "2,85", "Norges Bank %PN": "10,63", "Norges Bank %TOTAL": "5,64", "Oceana Investimentos Administradora de Carteira de Valores\n2,75 %ON": "9,81", "Oceana Investimentos Administradora de Carteira de Valores\n2,75 %PN": "5,28\nMobili\u00e1rios", "Oceana Investimentos Administradora de Carteira de Valores\n2,75 %TOTAL": "Ltda", "Shopping Center Reunidos Do Brasil Ltda. ((cid:0)scrb(cid:0)) %ON": "0,00", "Shopping Center Reunidos Do Brasil Ltda. ((cid:0)scrb(cid:0)) %PN": "0,00", "Shopping Center Reunidos Do Brasil Ltda. ((cid:0)scrb(cid:0)) %TOTAL": "0,00", "Vera Ribeiro Jereissati %ON": "1,73", "Vera Ribeiro Jereissati %PN": "0,00", "Vera Ribeiro Jereissati %TOTAL": "1,11", "Outros %ON": "24,70", "Outros %PN": "71,85", "Outros %TOTAL": "41,61", "A\u00e7\u00f5es Tesouraria %ON": "0,23", "A\u00e7\u00f5es Tesouraria %PN": "0,81", "A\u00e7\u00f5es Tesouraria %TOTAL": "0,44"}, "A\u00e7\u00f5es em Circula\u00e7\u00e3o no Mercado": {"date": "01/02/2023", "csv": {"Pessoas F\u00edsicas - Quantidade": "56.072", "Pessoas F\u00edsicas - Percentual": "-", "Pessoas Jur\u00eddicas - Quantidade": "1.375", "Pessoas Jur\u00eddicas - Percentual": "-", "Investidores Institucionais - Quantidade": "49", "Investidores Institucionais - Percentual": "-", "Quantidade de A\u00e7\u00f5es Ordin\u00e1rias - Quantidade": "249.585.008", "Quantidade de A\u00e7\u00f5es Ordin\u00e1rias - Percentual": "36,65", "Quantidade de A\u00e7\u00f5es Preferenciais - Quantidade": "431.482.110", "Quantidade de A\u00e7\u00f5es Preferenciais - Percentual": "63,35"}}, "Composi\u00e7\u00e3o do Capital Social": {"date": "01/02/2023", "csv": {"Tipos de Investidores": "/", "Total de A\u00e7\u00f5es": "681.067.118", "-": "01/02/2023", "Ordin\u00e1rias": "785.167.052", "Preferenciais": "439.642.726", "Total": "1.224.809.778"}}}, "itub4.pdf": {"Dados da Companhia": {"csv": {"Nome de Preg\u00e3o:": "ITAUUNIBANCO", "C\u00f3digos de Negocia\u00e7\u00e3o:": "Mais C\u00f3digos\nITUB3; ITUB4", "CNPJ:": "60.872.504/0001-23", "Atividade Principal:": "A Sociedade Tem Por Objeto A Atividade\nBanc\u00e1ria em Todas As Modalidades\nAutorizadas. Inclusive A de Opera\u00e7\u00f5es de\nC\u00e2mbio.", "Classi\u0000ca\u00e7\u00e3o Setorial:": "Financeiro / Intermedi\u00e1rios Financeiros /\nBancos", "Site:": "www.itau-unibanco.com.br/relacoes-com-\ninvestidores (http://www.itau-\nunibanco.com.br/relacoes-com-\ninvestidores)"}}, "Dados Econ\u00f4mico-Financeiros - R$ - mil": {"Balan\u00e7o Patrimonial - Consolidado": {"csv": {"Ativo Imobilizado, Investimentos e Intang\u00edvel - Inicial": "30.881.000", "Ativo Imobilizado, Investimentos e Intang\u00edvel - Final": "32.499.000", "Ativo Total - Inicial": "2.321.066.000", "Ativo Total - Final": "2.543.100.000", "Patrim\u00f4nio L\u00edquido - Inicial": "177.107.000", "Patrim\u00f4nio L\u00edquido - Final": "199.050.000", "Patrim\u00f4nio L\u00edquido Atribu\u00eddo \u00e0 Controladora - Inicial": "167.717.000", "Patrim\u00f4nio L\u00edquido Atribu\u00eddo \u00e0 Controladora - Final": "190.177.000"}, "Inicio": "31/12/2022", "Fim": "31/12/2023"}, "Demonstra\u00e7\u00e3o do Resultado - Consolidado": {"csv": {"Receita da Intermedia\u00e7\u00e3o Financeira - Inicial": "259.026.000", "Receita da Intermedia\u00e7\u00e3o Financeira - Final": "313.221.000", "Resultado Bruto da Intermedia\u00e7\u00e3o Financeira - Inicial": "114.542.000", "Resultado Bruto da Intermedia\u00e7\u00e3o Financeira - Final": "124.526.000", "Resultado de Equival\u00eancia Patrimonial - Inicial": "672.000", "Resultado de Equival\u00eancia Patrimonial - Final": "920.000", "Resultado L\u00edquido das Opera\u00e7\u00f5es Continuadas - Inicial": "30.242.000", "Resultado L\u00edquido das Opera\u00e7\u00f5es Continuadas - Final": "33.877.000", "Lucro (Preju\u00edzo) do Per\u00edodo - Inicial": "30.242.000", "Lucro (Preju\u00edzo) do Per\u00edodo - Final": "33.877.000", "Lucro (Preju\u00edzo) do Per\u00edodo Atribu\u00eddo \u00e0 Controladora - Inicial": "29.207.000", "Lucro (Preju\u00edzo) do Per\u00edodo Atribu\u00eddo \u00e0 Controladora - Final": "33.105.000"}, "Inicio": "01/01/2022 a\n31/12/2022", "Fim": "01/01/2023 a\n31/12/2023"}, "Demonstra\u00e7\u00e3o do Fluxo de Caixa - Consolidado": {"csv": {"Atividades Operacionais - Inicial": "129.633.000", "Atividades Operacionais - Final": "77.493.000", "Atividades de Investimento - Inicial": "(73.270.000)", "Atividades de Investimento - Final": "(31.230.000)", "Atividades de Financiamento - Inicial": "(31.714.000)", "Atividades de Financiamento - Final": "(22.448.000)", "Varia\u00e7\u00e3o Cambial sobre Caixa e Equivalentes - Inicial": "(24.279.000)", "Varia\u00e7\u00e3o Cambial sobre Caixa e Equivalentes - Final": "(11.529.000)", "Aumento (Redu\u00e7\u00e3o) de Caixa e Equivalentes - Inicial": "370.000", "Aumento (Redu\u00e7\u00e3o) de Caixa e Equivalentes - Final": "12.286.000"}, "Inicio": "01/01/2022 a\n31/12/2022", "Fim": "01/01/2023 a\n31/12/2023"}}, "Posi\u00e7\u00e3o Acion\u00e1ria*": {"Blackrock.inc %ON": "0,00", "Blackrock.inc %PN": "7,22", "Blackrock.inc %TOTAL": "3,57", "Gqg Partners Llc %ON": "0,00", "Gqg Partners Llc %PN": "5,23", "Gqg Partners Llc %TOTAL": "2,59", "Ita\u00fasa S.A. %ON": "39,21", "Ita\u00fasa S.A. %PN": "0,00", "Ita\u00fasa S.A. %TOTAL": "19,83", "Iupar - Ita\u00fa Unibanco Participa\u00e7\u00f5es S.A. %ON": "51,71", "Iupar - Ita\u00fa Unibanco Participa\u00e7\u00f5es S.A. %PN": "0,00", "Iupar - Ita\u00fa Unibanco Participa\u00e7\u00f5es S.A. %TOTAL": "26,15", "Outros %ON": "9,08", "Outros %PN": "87,46", "Outros %TOTAL": "47,82", "A\u00e7\u00f5es Tesouraria %ON": "0,00", "A\u00e7\u00f5es Tesouraria %PN": "0,09", "A\u00e7\u00f5es Tesouraria %TOTAL": "0,04"}, "A\u00e7\u00f5es em Circula\u00e7\u00e3o no Mercado": {"date": "25/04/2023", "csv": {"Pessoas F\u00edsicas - Quantidade": "464.049", "Pessoas F\u00edsicas - Percentual": "-", "Pessoas Jur\u00eddicas - Quantidade": "12.903", "Pessoas Jur\u00eddicas - Percentual": "-", "Investidores Institucionais - Quantidade": "1.422", "Investidores Institucionais - Percentual": "-", "Quantidade de A\u00e7\u00f5es Ordin\u00e1rias - Quantidade": "384.672.066", "Quantidade de A\u00e7\u00f5es Ordin\u00e1rias - Percentual": "7,76", "Quantidade de A\u00e7\u00f5es Preferenciais - Quantidade": "4.800.834.364", "Quantidade de A\u00e7\u00f5es Preferenciais - Percentual": "99,07", "Total de A\u00e7\u00f5es - Quantidade": "5.185.506.430", "Total de A\u00e7\u00f5es - Percentual": "52,89"}}, "Composi\u00e7\u00e3o do Capital Social": {"date": "31/01/2021", "csv": {"Ordin\u00e1rias": "4.958.290.359", "Preferenciais": "4.845.844.989", "Total": "9.804.135.348"}}}, "egie3.pdf": {"Dados da Companhia": {"csv": {"Nome de Preg\u00e3o:": "ENGIE BRASIL", "C\u00f3digos de Negocia\u00e7\u00e3o:": "Mais C\u00f3digos\nEGIE3", "CNPJ:": "02.474.103/0001-19", "Atividade Principal:": "Gera\u00e7\u00e3o. Comercializa\u00e7\u00e3o E Transmiss\u00e3o de\nEnergia El\u00e9trica", "Classi\u0000ca\u00e7\u00e3o Setorial:": "Utilidade P\u00fablica / Energia El\u00e9trica /\nEnergia El\u00e9trica", "Site:": "www.engie.com.br\n(http://www.engie.com.br)"}}, "Dados Econ\u00f4mico-Financeiros - R$ - mil": {"Balan\u00e7o Patrimonial - Consolidado": {"csv": {"Ativo Imobilizado, Investimentos e Intang\u00edvel - Inicial": "21.338.326", "Ativo Imobilizado, Investimentos e Intang\u00edvel - Final": "23.368.245", "Ativo Total - Inicial": "38.186.752", "Ativo Total - Final": "42.224.473", "Patrim\u00f4nio L\u00edquido - Inicial": "8.440.172", "Patrim\u00f4nio L\u00edquido - Final": "9.816.210", "Patrim\u00f4nio L\u00edquido Atribu\u00eddo \u00e0 Controladora - Inicial": "8.436.522", "Patrim\u00f4nio L\u00edquido Atribu\u00eddo \u00e0 Controladora - Final": "8.862.771"}, "Inicio": "31/12/2022", "Fim": "31/12/2023"}, "Demonstra\u00e7\u00e3o do Resultado - Consolidado": {"csv": {"Receita de Venda - Inicial": "11.906.605", "Receita de Venda - Final": "10.747.784", "Resultado Bruto - Inicial": "5.589.193", "Resultado Bruto - Final": "5.907.139", "Resultado de Equival\u00eancia Patrimonial - Inicial": "727.136", "Resultado de Equival\u00eancia Patrimonial - Final": "993.117", "Resultado Financeiro - Inicial": "(2.515.290)", "Resultado Financeiro - Final": "(1.962.998)", "Resultado L\u00edquido das Opera\u00e7\u00f5es Continuadas - Inicial": "2.664.568", "Resultado L\u00edquido das Opera\u00e7\u00f5es Continuadas - Final": "3.429.060", "Lucro (Preju\u00edzo) do Per\u00edodo - Inicial": "2.664.568", "Lucro (Preju\u00edzo) do Per\u00edodo - Final": "3.429.060", "Lucro (Preju\u00edzo) do Per\u00edodo Atribu\u00eddo \u00e0 Controladora - Inicial": "2.663.079", "Lucro (Preju\u00edzo) do Per\u00edodo Atribu\u00eddo \u00e0 Controladora - Final": "3.429.555"}, "Inicio": "01/01/2022 a\n31/12/2022", "Fim": "01/01/2023 a\n31/12/2023"}, "Demonstra\u00e7\u00e3o do Fluxo de Caixa - Consolidado": {"csv": {"Atividades Operacionais - Inicial": "3.337.493", "Atividades Operacionais - Final": "4.585.942", "Atividades de Investimento - Inicial": "(1.784.437)", "Atividades de Investimento - Final": "(2.042.414)", "Atividades de Financiamento - Inicial": "(4.473.575)", "Atividades de Financiamento - Final": "476.352", "Varia\u00e7\u00e3o Cambial sobre Caixa e Equivalentes - Inicial": "0", "Varia\u00e7\u00e3o Cambial sobre Caixa e Equivalentes - Final": "0", "Demonstra\u00e7\u00e3o do Fluxo de Caixa - Inicial": "Consolidado", "Demonstra\u00e7\u00e3o do Fluxo de Caixa - Final": "-", "Aumento (Redu\u00e7\u00e3o) de Caixa e Equivalentes - Inicial": "(2.920.519)", "Aumento (Redu\u00e7\u00e3o) de Caixa e Equivalentes - Final": "3.019.880"}, "Inicio": "01/01/2022 a\n31/12/2022", "Fim": "01/01/2023 a\n31/12/2023"}}, "Posi\u00e7\u00e3o Acion\u00e1ria*": {"Banco Cl\u00e1ssico S.A. %ON": "9,86", "Banco Cl\u00e1ssico S.A. %PN": "0,00", "Banco Cl\u00e1ssico S.A. %TOTAL": "9,86", "Engie Brasil Participa\u00e7\u00f5es Ltda. %ON": "68,71", "Engie Brasil Participa\u00e7\u00f5es Ltda. %PN": "0,00", "Engie Brasil Participa\u00e7\u00f5es Ltda. %TOTAL": "68,71", "Outros %ON": "21,43", "Outros %PN": "0,00", "Outros %TOTAL": "21,43", "A\u00e7\u00f5es Tesouraria %ON": "0,00", "A\u00e7\u00f5es Tesouraria %PN": "0,00", "A\u00e7\u00f5es Tesouraria %TOTAL": "0,00"}, "A\u00e7\u00f5es em Circula\u00e7\u00e3o no Mercado": {"date": "28/04/2022", "csv": {"Pessoas F\u00edsicas - Quantidade": "253.048", "Pessoas F\u00edsicas - Percentual": "-", "Pessoas Jur\u00eddicas - Quantidade": "8.166", "Pessoas Jur\u00eddicas - Percentual": "-", "Investidores Institucionais - Quantidade": "1.122", "Investidores Institucionais - Percentual": "-", "Quantidade de A\u00e7\u00f5es Ordin\u00e1rias - Quantidade": "255.208.461", "Quantidade de A\u00e7\u00f5es Ordin\u00e1rias - Percentual": "31,28", "Total de A\u00e7\u00f5es - Quantidade": "255.208.461", "Total de A\u00e7\u00f5es - Percentual": "31,28"}}, "Composi\u00e7\u00e3o do Capital Social": {"date": "07/12/2018", "csv": {"Ordin\u00e1rias": "815.927.740", "Preferenciais": "0", "Total": "815.927.740"}}}, "bbse3.pdf": {"Dados da Companhia": {"csv": {"Nome de Preg\u00e3o:": "BBSEGURIDADE", "C\u00f3digos de Negocia\u00e7\u00e3o:": "Mais C\u00f3digos\nBBSE3", "CNPJ:": "17.344.597/0001-94", "Atividade Principal:": "Participa\u00e7\u00e3o No Capital Social de Outras\nSociedades Que Realizem Quaisquer\nAtividades Reguladas Pela Susep E Ans.\nAl\u00e9m de Corretagem Desses Produtos.", "Classi\u0000ca\u00e7\u00e3o Setorial:": "Financeiro / Previd\u00eancia e Seguros /\nSeguradoras", "Site:": "www.bbseguridaderi.com.br\n(http://www.bbseguridaderi.com.br)"}}, "Dados Econ\u00f4mico-Financeiros - R$ - mil": {"Balan\u00e7o Patrimonial - Consolidado": {"csv": {"Ativo Imobilizado, Investimentos e Intang\u00edvel - Inicial": "7.961.460", "Ativo Imobilizado, Investimentos e Intang\u00edvel - Final": "9.335.492", "Ativo Total - Inicial": "16.570.461", "Ativo Total - Final": "18.272.622", "Patrim\u00f4nio L\u00edquido - Inicial": "8.036.730", "Patrim\u00f4nio L\u00edquido - Final": "9.816.482", "Patrim\u00f4nio L\u00edquido Atribu\u00eddo \u00e0 Controladora - Inicial": "8.036.730", "Patrim\u00f4nio L\u00edquido Atribu\u00eddo \u00e0 Controladora - Final": "9.816.482"}, "Inicio": "31/12/2022", "Fim": "31/12/2023"}, "Demonstra\u00e7\u00e3o do Resultado - Consolidado": {"csv": {"Receitas das Opera\u00e7\u00f5es - Inicial": "0", "Receitas das Opera\u00e7\u00f5es - Final": "0", "Resultado Bruto - Inicial": "0", "Resultado Bruto - Final": "0", "Resultado de Equival\u00eancia Patrimonial - Inicial": "3.515.609", "Resultado de Equival\u00eancia Patrimonial - Final": "4.890.458", "Resultado Financeiro - Inicial": "502.562", "Resultado Financeiro - Final": "587.545", "Resultado L\u00edquido das Opera\u00e7\u00f5es Continuadas - Inicial": "6.196.415", "Resultado L\u00edquido das Opera\u00e7\u00f5es Continuadas - Final": "7.947.203", "Lucro (Preju\u00edzo) do Per\u00edodo - Inicial": "6.196.415", "Lucro (Preju\u00edzo) do Per\u00edodo - Final": "7.947.203", "Lucro (Preju\u00edzo) do Per\u00edodo Atribu\u00eddo \u00e0 Controladora - Inicial": "6.196.415", "Lucro (Preju\u00edzo) do Per\u00edodo Atribu\u00eddo \u00e0 Controladora - Final": "7.947.203"}, "Inicio": "01/01/2022 a\n31/12/2022", "Fim": "01/01/2023 a\n31/12/2023"}, "Demonstra\u00e7\u00e3o do Fluxo de Caixa - Consolidado": {"csv": {"Atividades Operacionais - Inicial": "3.275.011", "Atividades Operacionais - Final": "3.697.841", "Atividades de Investimento - Inicial": "2.636.797", "Atividades de Investimento - Final": "2.563.562", "Demonstra\u00e7\u00e3o do Fluxo de Caixa - Inicial": "Consolidado", "Demonstra\u00e7\u00e3o do Fluxo de Caixa - Final": "-", "Atividades de Financiamento - Inicial": "(3.925.751)", "Atividades de Financiamento - Final": "(7.585.279)", "Varia\u00e7\u00e3o Cambial sobre Caixa e Equivalentes - Inicial": "0", "Varia\u00e7\u00e3o Cambial sobre Caixa e Equivalentes - Final": "0", "Aumento (Redu\u00e7\u00e3o) de Caixa e Equivalentes - Inicial": "1.986.057", "Aumento (Redu\u00e7\u00e3o) de Caixa e Equivalentes - Final": "(1.323.876)"}, "Inicio": "01/01/2022 a\n31/12/2022", "Fim": "01/01/2023 a\n31/12/2023"}}, "Posi\u00e7\u00e3o Acion\u00e1ria*": {"Banco Do Brasil S.A. %ON": "66,25", "Banco Do Brasil S.A. %PN": "0,00", "Banco Do Brasil S.A. %TOTAL": "66,25", "Outros %ON": "33,59", "Outros %PN": "0,00", "Outros %TOTAL": "33,59", "A\u00e7\u00f5es Tesouraria %ON": "0,16", "A\u00e7\u00f5es Tesouraria %PN": "0,00", "A\u00e7\u00f5es Tesouraria %TOTAL": "0,16"}, "A\u00e7\u00f5es em Circula\u00e7\u00e3o no Mercado": {"date": "29/04/2022", "csv": {"Pessoas F\u00edsicas - Quantidade": "351.530", "Pessoas F\u00edsicas - Percentual": "-", "Pessoas Jur\u00eddicas - Quantidade": "2.572", "Pessoas Jur\u00eddicas - Percentual": "-", "Investidores Institucionais - Quantidade": "1.310", "Investidores Institucionais - Percentual": "-", "Quantidade de A\u00e7\u00f5es Ordin\u00e1rias - Quantidade": "671.682.536", "Quantidade de A\u00e7\u00f5es Ordin\u00e1rias - Percentual": "33,58", "Total de A\u00e7\u00f5es - Quantidade": "671.682.536", "Total de A\u00e7\u00f5es - Percentual": "33,58"}}, "Composi\u00e7\u00e3o do Capital Social": {"date": "29/04/2022", "csv": {"Ordin\u00e1rias": "2.000.000.000", "Preferenciais": "0", "Total": "2.000.000.000"}}}, "tims3.pdf": {"Dados da Companhia": {"csv": {"Nome de Preg\u00e3o:": "TIM", "C\u00f3digos de Negocia\u00e7\u00e3o:": "Mais C\u00f3digos\nTIMS3", "CNPJ:": "02.421.421/0001-11", "Atividade Principal:": "", "Classi\u0000ca\u00e7\u00e3o Setorial:": "Comunica\u00e7\u00f5es / Telecomunica\u00e7\u00f5es /\nTelecomunica\u00e7\u00f5es"}}, "Dados Econ\u00f4mico-Financeiros - R$ - mil": {"Balan\u00e7o Patrimonial - Consolidado": {"csv": {"Ativo Imobilizado, Investimentos e Intang\u00edvel - Inicial": "40.617.816", "Ativo Imobilizado, Investimentos e Intang\u00edvel - Final": "39.487.668", "Ativo Total - Inicial": "56.408.367", "Ativo Total - Final": "55.260.156", "Patrim\u00f4nio L\u00edquido - Inicial": "25.397.365", "Patrim\u00f4nio L\u00edquido - Final": "26.015.940", "Patrim\u00f4nio L\u00edquido Atribu\u00eddo \u00e0 Controladora - Inicial": "25.397.365", "Patrim\u00f4nio L\u00edquido Atribu\u00eddo \u00e0 Controladora - Final": "26.015.940"}, "Inicio": "31/12/2022", "Fim": "31/12/2023"}, "Demonstra\u00e7\u00e3o do Resultado - Consolidado": {"csv": {"Receita de Venda - Inicial": "21.530.801", "Receita de Venda - Final": "23.833.893", "Resultado Bruto - Inicial": "10.874.820", "Resultado Bruto - Final": "12.337.456", "Resultado de Equival\u00eancia Patrimonial - Inicial": "(61.587)", "Resultado de Equival\u00eancia Patrimonial - Final": "(89.304)", "Resultado Financeiro - Inicial": "(1.439.008)", "Resultado Financeiro - Final": "(1.533.265)", "Resultado L\u00edquido das Opera\u00e7\u00f5es Continuadas - Inicial": "1.670.755", "Resultado L\u00edquido das Opera\u00e7\u00f5es Continuadas - Final": "2.837.422", "Lucro (Preju\u00edzo) do Per\u00edodo - Inicial": "1.670.755", "Lucro (Preju\u00edzo) do Per\u00edodo - Final": "2.837.422", "Lucro (Preju\u00edzo) do Per\u00edodo Atribu\u00eddo \u00e0 Controladora - Inicial": "0", "Lucro (Preju\u00edzo) do Per\u00edodo Atribu\u00eddo \u00e0 Controladora - Final": "0"}, "Inicio": "01/01/2022 a\n31/12/2022", "Fim": "01/01/2023 a\n31/12/2023"}, "Demonstra\u00e7\u00e3o do Fluxo de Caixa - Consolidado": {"csv": {"Atividades Operacionais - Inicial": "9.162.259", "Atividades Operacionais - Final": "12.420.656", "Atividades de Investimento - Inicial": "(8.353.129)", "Atividades de Investimento - Final": "(4.683.538)", "Atividades de Financiamento - Inicial": "(3.489.032)", "Atividades de Financiamento - Final": "(7.207.900)", "Varia\u00e7\u00e3o Cambial sobre Caixa e Equivalentes - Inicial": "0", "Varia\u00e7\u00e3o Cambial sobre Caixa e Equivalentes - Final": "0", "Aumento (Redu\u00e7\u00e3o) de Caixa e Equivalentes - Inicial": "(2.679.902)", "Aumento (Redu\u00e7\u00e3o) de Caixa e Equivalentes - Final": "529.218"}, "Inicio": "01/01/2022 a\n31/12/2022", "Fim": "01/01/2023 a\n31/12/2023"}}, "Posi\u00e7\u00e3o Acion\u00e1ria*": {"Tim Brasil Servi\u00e7os E Participa\u00e7\u00f5es S.A. %ON": "66,60", "Tim Brasil Servi\u00e7os E Participa\u00e7\u00f5es S.A. %PN": "0,00", "Tim Brasil Servi\u00e7os E Participa\u00e7\u00f5es S.A. %TOTAL": "66,60", "Outros %ON": "33,40", "Outros %PN": "0,00", "Outros %TOTAL": "33,40", "A\u00e7\u00f5es Tesouraria %ON": "0,00", "A\u00e7\u00f5es Tesouraria %PN": "0,00", "A\u00e7\u00f5es Tesouraria %TOTAL": "0,00"}, "A\u00e7\u00f5es em Circula\u00e7\u00e3o no Mercado": {"date": "29/03/2022", "csv": {"Pessoas F\u00edsicas - Quantidade": "1.259.476", "Pessoas F\u00edsicas - Percentual": "-", "Pessoas Jur\u00eddicas - Quantidade": "229.157", "Pessoas Jur\u00eddicas - Percentual": "-", "Investidores Institucionais - Quantidade": "83", "Investidores Institucionais - Percentual": "-", "Quantidade de A\u00e7\u00f5es Ordin\u00e1rias - Quantidade": "808.436.195", "Quantidade de A\u00e7\u00f5es Ordin\u00e1rias - Percentual": "33,39", "Total de A\u00e7\u00f5es - Quantidade": "808.436.195", "Total de A\u00e7\u00f5es - Percentual": "33,39"}}, "Composi\u00e7\u00e3o do Capital Social": {"date": "28/09/2020", "csv": {"Ordin\u00e1rias": "2.420.804.398", "Preferenciais": "0", "Total": "2.420.804.398"}}}, "petr3.pdf": {"Dados da Companhia": {"csv": {"Nome de Preg\u00e3o:": "PETROBRAS", "C\u00f3digos de Negocia\u00e7\u00e3o:": "Mais C\u00f3digos\nPETR3; PETR4", "CNPJ:": "33.000.167/0001-01", "Atividade Principal:": "Pesquisa. Lavra. Re\u0000na\u00e7\u00e3o. Processamento.\nCom\u00e9rcio E Transporte de Petr\u00f3leo. de Seus\nDerivados. de G\u00e1s Natural E de Outros\nHidrocarbonetos Fluidos. Al\u00e9m Das\nAtividades Vinculadas \u00e0 Energia.", "Classi\u0000ca\u00e7\u00e3o Setorial:": "Petr\u00f3leo. G\u00e1s e Biocombust\u00edveis / Petr\u00f3leo.\nG\u00e1s e Biocombust\u00edveis / Explora\u00e7\u00e3o. Re\u0000no\ne Distribui\u00e7\u00e3o", "Site:": "www.petrobras.com.br\n(http://www.petrobras.com.br)"}}, "Dados Econ\u00f4mico-Financeiros - R$ - mil": {"Balan\u00e7o Patrimonial - Consolidado": {"csv": {"Ativo Imobilizado, Investimentos e Intang\u00edvel - Inicial": "702.935.000", "Ativo Imobilizado, Investimentos e Intang\u00edvel - Final": "764.074.000", "Ativo Total - Inicial": "976.709.000", "Ativo Total - Final": "1.050.888.000", "Patrim\u00f4nio L\u00edquido - Inicial": "364.385.000", "Patrim\u00f4nio L\u00edquido - Final": "382.340.000", "Patrim\u00f4nio L\u00edquido Atribu\u00eddo \u00e0 Controladora - Inicial": "362.594.000", "Patrim\u00f4nio L\u00edquido Atribu\u00eddo \u00e0 Controladora - Final": "380.441.000"}, "Inicio": "31/12/2022", "Fim": "31/12/2023"}, "Demonstra\u00e7\u00e3o do Resultado - Consolidado": {"csv": {"Receita de Venda - Inicial": "641.256.000", "Receita de Venda - Final": "511.994.000", "Resultado Bruto - Inicial": "334.100.000", "Resultado Bruto - Final": "269.933.000", "Resultado de Equival\u00eancia Patrimonial - Inicial": "1.291.000", "Resultado de Equival\u00eancia Patrimonial - Final": "(1.480.000)", "Resultado Financeiro - Inicial": "(19.257.000)", "Resultado Financeiro - Final": "(11.861.000)", "Resultado L\u00edquido das Opera\u00e7\u00f5es Continuadas - Inicial": "189.005.000", "Resultado L\u00edquido das Opera\u00e7\u00f5es Continuadas - Final": "125.166.000", "Lucro (Preju\u00edzo) do Per\u00edodo - Inicial": "189.005.000", "Lucro (Preju\u00edzo) do Per\u00edodo - Final": "125.166.000", "Lucro (Preju\u00edzo) do Per\u00edodo Atribu\u00eddo \u00e0 Controladora - Inicial": "188.328.000", "Lucro (Preju\u00edzo) do Per\u00edodo Atribu\u00eddo \u00e0 Controladora - Final": "124.606.000"}, "Inicio": "01/01/2022 a\n31/12/2022", "Fim": "01/01/2023 a\n31/12/2023"}, "Demonstra\u00e7\u00e3o do Fluxo de Caixa - Consolidado": {"csv": {"Atividades Operacionais - Inicial": "255.410.000", "Atividades Operacionais - Final": "215.696.000", "Atividades de Investimento - Inicial": "(4.377.000)", "Atividades de Investimento - Final": "(39.495.000)", "Atividades de Financiamento - Inicial": "(264.156.000)", "Atividades de Financiamento - Final": "(153.435.000)", "Varia\u00e7\u00e3o Cambial sobre Caixa e Equivalentes - Inicial": "(3.636.000)", "Varia\u00e7\u00e3o Cambial sobre Caixa e Equivalentes - Final": "(2.876.000)", "Aumento (Redu\u00e7\u00e3o) de Caixa e Equivalentes - Inicial": "(16.759.000)", "Aumento (Redu\u00e7\u00e3o) de Caixa e Equivalentes - Final": "19.890.000"}, "Inicio": "01/01/2022 a\n31/12/2022", "Fim": "01/01/2023 a\n31/12/2023"}}, "Posi\u00e7\u00e3o Acion\u00e1ria*": {"Banco Nacional de Desenvolvimento Econ\u00f4mico E Social - Bndes %ON": "0,00", "Banco Nacional de Desenvolvimento Econ\u00f4mico E Social - Bndes %PN": "2,41", "Banco Nacional de Desenvolvimento Econ\u00f4mico E Social - Bndes %TOTAL": "1,04", "Bndes Participa\u00e7\u00f5es - Bndespar %ON": "0,00", "Bndes Participa\u00e7\u00f5es - Bndespar %PN": "16,07", "Bndes Participa\u00e7\u00f5es - Bndespar %TOTAL": "6,90", "Blackrock Inc %ON": "0,00", "Blackrock Inc %PN": "5,01", "Blackrock Inc %TOTAL": "2,15", "Gqg Partners Llc %ON": "5,64", "Gqg Partners Llc %PN": "5,20", "Gqg Partners Llc %TOTAL": "5,45", "Uni\u00e3o Federal %ON": "50,26", "Uni\u00e3o Federal %PN": "0,00", "Uni\u00e3o Federal %TOTAL": "28,68", "Outros %ON": "44,10", "Outros %PN": "71,31", "Outros %TOTAL": "55,78", "A\u00e7\u00f5es Tesouraria %ON": "0,00", "A\u00e7\u00f5es Tesouraria %PN": "0,00", "A\u00e7\u00f5es Tesouraria %TOTAL": "0,00"}, "A\u00e7\u00f5es em Circula\u00e7\u00e3o no Mercado": {"date": "30/11/2022", "csv": {"Pessoas F\u00edsicas - Quantidade": "858.992", "Pessoas F\u00edsicas - Percentual": "-", "Pessoas Jur\u00eddicas - Quantidade": "5.807", "Pessoas Jur\u00eddicas - Percentual": "-", "Investidores Institucionais - Quantidade": "2.748", "Investidores Institucionais - Percentual": "-", "Quantidade de A\u00e7\u00f5es Ordin\u00e1rias - Quantidade": "3.701.760.571", "Quantidade de A\u00e7\u00f5es Ordin\u00e1rias - Percentual": "49,74", "Quantidade de A\u00e7\u00f5es Preferenciais - Quantidade": "4.566.511.125", "Quantidade de A\u00e7\u00f5es Preferenciais - Percentual": "81,52", "Total de A\u00e7\u00f5es - Quantidade": "8.268.271.696", "Total de A\u00e7\u00f5es - Percentual": "63,39"}}, "Composi\u00e7\u00e3o do Capital Social": {"date": "02/04/2014", "csv": {"Ordin\u00e1rias": "7.442.454.142", "Preferenciais": "5.602.042.788", "Total": "13.044.496.930"}}}, "ciel3.pdf": {"Dados da Companhia": {"csv": {"Nome de Preg\u00e3o:": "CIELO", "C\u00f3digos de Negocia\u00e7\u00e3o:": "Mais C\u00f3digos\nCIEL3", "CNPJ:": "01.027.058/0001-91", "Atividade Principal:": "Empresa Prestadora de Servi\u00e7os de\nAdquir\u00eancia E Meios de Pagamento.", "Classi\u0000ca\u00e7\u00e3o Setorial:": "Financeiro / Servi\u00e7os Financeiros Diversos /\nServi\u00e7os Financeiros Diversos", "Site:": "www.cielo.com.br (http://www.cielo.com.br)"}}, "Dados Econ\u00f4mico-Financeiros - R$ - mil": {"Balan\u00e7o Patrimonial - Consolidado": {"csv": {"Ativo Imobilizado, Investimentos e Intang\u00edvel - Inicial": "10.078.007", "Ativo Imobilizado, Investimentos e Intang\u00edvel - Final": "9.647.801", "Ativo Total - Inicial": "109.784.818", "Ativo Total - Final": "107.782.200", "Patrim\u00f4nio L\u00edquido - Inicial": "13.816.772", "Patrim\u00f4nio L\u00edquido - Final": "14.984.852", "Patrim\u00f4nio L\u00edquido Atribu\u00eddo \u00e0 Controladora - Inicial": "10.950.834", "Patrim\u00f4nio L\u00edquido Atribu\u00eddo \u00e0 Controladora - Final": "12.281.359"}, "Inicio": "31/12/2022", "Fim": "31/12/2023"}, "Demonstra\u00e7\u00e3o do Resultado - Consolidado": {"csv": {"Receita de Venda - Inicial": "10.693.106", "Receita de Venda - Final": "10.601.105", "Resultado Bruto - Inicial": "4.424.352", "Resultado Bruto - Final": "4.991.656", "Resultado de Equival\u00eancia Patrimonial - Inicial": "0", "Resultado de Equival\u00eancia Patrimonial - Final": "0", "Resultado Financeiro - Inicial": "(386.300)", "Resultado Financeiro - Final": "(154.653)", "Resultado L\u00edquido das Opera\u00e7\u00f5es Continuadas - Inicial": "1.714.680", "Resultado L\u00edquido das Opera\u00e7\u00f5es Continuadas - Final": "2.468.466", "Lucro (Preju\u00edzo) do Per\u00edodo - Inicial": "1.714.680", "Lucro (Preju\u00edzo) do Per\u00edodo - Final": "2.468.466", "Lucro (Preju\u00edzo) do Per\u00edodo Atribu\u00eddo \u00e0 Controladora - Inicial": "1.411.468", "Lucro (Preju\u00edzo) do Per\u00edodo Atribu\u00eddo \u00e0 Controladora - Final": "2.087.137"}, "Inicio": "01/01/2022 a\n31/12/2022", "Fim": "01/01/2023 a\n31/12/2023"}, "Demonstra\u00e7\u00e3o do Fluxo de Caixa - Consolidado": {"csv": {"Atividades Operacionais - Inicial": "(2.131.202)", "Atividades Operacionais - Final": "959.307", "Atividades de Investimento - Inicial": "(55.181)", "Atividades de Investimento - Final": "(505.864)", "Demonstra\u00e7\u00e3o do Fluxo de Caixa - Inicial": "Consolidado", "Demonstra\u00e7\u00e3o do Fluxo de Caixa - Final": "-", "Atividades de Financiamento - Inicial": "(1.270.954)", "Atividades de Financiamento - Final": "(1.082.145)", "Varia\u00e7\u00e3o Cambial sobre Caixa e Equivalentes - Inicial": "0", "Varia\u00e7\u00e3o Cambial sobre Caixa e Equivalentes - Final": "0", "Aumento (Redu\u00e7\u00e3o) de Caixa e Equivalentes - Inicial": "(3.457.337)", "Aumento (Redu\u00e7\u00e3o) de Caixa e Equivalentes - Final": "(628.702)"}, "Inicio": "01/01/2022 a\n31/12/2022", "Fim": "01/01/2023 a\n31/12/2023"}}, "Posi\u00e7\u00e3o Acion\u00e1ria*": {"Bb Elo Cart\u00f5es Participa\u00e7\u00f5es S.A. %ON": "28,65", "Bb Elo Cart\u00f5es Participa\u00e7\u00f5es S.A. %PN": "0,00", "Bb Elo Cart\u00f5es Participa\u00e7\u00f5es S.A. %TOTAL": "28,65", "Quixaba Empreendimentos E Participa\u00e7\u00f5es Ltda %ON": "30,06", "Quixaba Empreendimentos E Participa\u00e7\u00f5es Ltda %PN": "0,00", "Quixaba Empreendimentos E Participa\u00e7\u00f5es Ltda %TOTAL": "30,06", "Outros %ON": "40,38", "Outros %PN": "0,00", "Outros %TOTAL": "40,38", "A\u00e7\u00f5es Tesouraria %ON": "0,92", "A\u00e7\u00f5es Tesouraria %PN": "0,00", "A\u00e7\u00f5es Tesouraria %TOTAL": "0,92"}, "A\u00e7\u00f5es em Circula\u00e7\u00e3o no Mercado": {"date": "27/04/2022", "csv": {"Pessoas F\u00edsicas - Quantidade": "184.967", "Pessoas F\u00edsicas - Percentual": "-", "Pessoas Jur\u00eddicas - Quantidade": "1.292", "Pessoas Jur\u00eddicas - Percentual": "-", "Investidores Institucionais - Quantidade": "291", "Investidores Institucionais - Percentual": "-", "Quantidade de A\u00e7\u00f5es Ordin\u00e1rias - Quantidade": "1.095.401.258", "Quantidade de A\u00e7\u00f5es Ordin\u00e1rias - Percentual": "40,32", "Total de A\u00e7\u00f5es - Quantidade": "1.095.401.258", "Total de A\u00e7\u00f5es - Percentual": "40,32"}}, "Composi\u00e7\u00e3o do Capital Social": {"date": "20/04/2018", "csv": {"Ordin\u00e1rias": "2.716.815.061", "Preferenciais": "0", "Total": "2.716.815.061"}}}, "azul4.pdf": {"Dados da Companhia": {"csv": {"Nome de Preg\u00e3o:": "AZUL", "C\u00f3digos de Negocia\u00e7\u00e3o:": "Mais C\u00f3digos\nAZUL4", "CNPJ:": "09.305.994/0001-29", "Atividade Principal:": "Transporte E Log\u00edstica", "Classi\u0000ca\u00e7\u00e3o Setorial:": "Bens Industriais / Transporte / Transporte\nA\u00e9reo", "Site:": "www.voeazul.com.br\n(http://www.voeazul.com.br)"}}, "Dados Econ\u00f4mico-Financeiros - R$ - mil": {"Balan\u00e7o Patrimonial - Consolidado": {"csv": {"Ativo Imobilizado, Investimentos e Intang\u00edvel - Inicial": "10.932.160", "Ativo Imobilizado, Investimentos e Intang\u00edvel - Final": "11.234.848", "Ativo Total - Inicial": "18.721.293", "Ativo Total - Final": "19.605.095", "Patrim\u00f3nio L\u00edquido - Inicial": "(19.007.500)", "Patrim\u00f3nio L\u00edquido - Final": "(21.286.126)", "Patrim\u00f4nio L\u00edquido Atribu\u00eddo \u00e0 Controladora - Inicial": "(19.007.500)", "Patrim\u00f4nio L\u00edquido Atribu\u00eddo \u00e0 Controladora - Final": "(21.286.126)"}, "Inicio": "31/12/2022", "Fim": "30/09/2023"}, "Demonstra\u00e7\u00e3o do Resultado - Consolidado": {"csv": {"Receita de Venda - Inicial": "11.494.615", "Receita de Venda - Final": "13.648.963", "Resultado Bruto - Inicial": "1.339.076", "Resultado Bruto - Final": "2.371.849", "Resultado de Equival\u00eancia Patrimonial - Inicial": "0", "Resultado de Equival\u00eancia Patrimonial - Final": "0", "Resultado Financeiro - Inicial": "(2.166.271)", "Resultado Financeiro - Final": "(3.468.705)", "Resultado L\u00edquido das Opera\u00e7\u00f5es Continuadas - Inicial": "(1.828.420)", "Resultado L\u00edquido das Opera\u00e7\u00f5es Continuadas - Final": "(2.327.619)", "Lucro (Preju\u00edzo) do Per\u00edodo - Inicial": "(1.828.420)", "Lucro (Preju\u00edzo) do Per\u00edodo - Final": "(2.327.619)", "Lucro (Preju\u00edzo) do Per\u00edodo Atribu\u00eddo \u00e0 Controladora - Inicial": "0", "Lucro (Preju\u00edzo) do Per\u00edodo Atribu\u00eddo \u00e0 Controladora - Final": "0"}, "Inicio": "01/01/2022 a\n30/09/2022", "Fim": "01/01/2023 a\n30/09/2023"}, "Demonstra\u00e7\u00e3o do Fluxo de Caixa - Consolidado": {"csv": {"Atividades Operacionais - Inicial": "1.603.988", "Atividades Operacionais - Final": "1.540.904", "Atividades de Investimento - Inicial": "(414.420)", "Atividades de Investimento - Final": "(729.776)", "Atividades de Financiamento - Inicial": "(3.174.811)", "Atividades de Financiamento - Final": "(142.764)", "Varia\u00e7\u00e3o Cambial sobre Caixa e Equivalentes - Inicial": "15.192", "Varia\u00e7\u00e3o Cambial sobre Caixa e Equivalentes - Final": "62.680", "Aumento (Redu\u00e7\u00e3o) de Caixa e Equivalentes - Inicial": "(1.970.051)", "Aumento (Redu\u00e7\u00e3o) de Caixa e Equivalentes - Final": "731.044"}, "Inicio": "01/01/2022 a\n30/09/2022", "Fim": "01/01/2023 a\n30/09/2023"}}, "Posi\u00e7\u00e3o Acion\u00e1ria*": {"Cal\u0000nco. Inc. %ON": "0,00", "Cal\u0000nco. Inc. %PN": "5,55", "Cal\u0000nco. Inc. %TOTAL": "1,47", "David Gary Neeleman %ON": "67,00", "David Gary Neeleman %PN": "2,07", "David Gary Neeleman %TOTAL": "49,76", "Rio Novo Loca\u00e7\u00f5es Ltda. %ON": "2,64", "Rio Novo Loca\u00e7\u00f5es Ltda. %PN": "0,00", "Rio Novo Loca\u00e7\u00f5es Ltda. %TOTAL": "1,94", "Saleb Ii Founder 1 Llc %ON": "0,00", "Saleb Ii Founder 1 Llc %PN": "0,12", "Saleb Ii Founder 1 Llc %TOTAL": "0,03", "Trip Investimentos Ltda. %ON": "8,58", "Trip Investimentos Ltda. %PN": "0,90", "Trip Investimentos Ltda. %TOTAL": "6,54", "Trip Participa\u00e7\u00f5es S.A. %ON": "21,78", "Trip Participa\u00e7\u00f5es S.A. %PN": "3,11", "Trip Participa\u00e7\u00f5es S.A. %TOTAL": "16,82", "Outros %ON": "0,00", "Outros %PN": "88,04", "Outros %TOTAL": "23,37", "A\u00e7\u00f5es Tesouraria %ON": "0,00", "A\u00e7\u00f5es Tesouraria %PN": "0,21", "A\u00e7\u00f5es Tesouraria %TOTAL": "0,06"}, "A\u00e7\u00f5es em Circula\u00e7\u00e3o no Mercado": {"date": "28/04/2022", "csv": {"Pessoas F\u00edsicas - Quantidade": "133.095", "Pessoas F\u00edsicas - Percentual": "-", "Pessoas Jur\u00eddicas - Quantidade": "714", "Pessoas Jur\u00eddicas - Percentual": "-", "Investidores Institucionais - Quantidade": "395", "Investidores Institucionais - Percentual": "-", "Quantidade de A\u00e7\u00f5es Ordin\u00e1rias - Quantidade": "306.558.420", "Quantidade de A\u00e7\u00f5es Ordin\u00e1rias - Percentual": "33,00", "Quantidade de A\u00e7\u00f5es Preferenciais - Quantidade": "327.646.296", "Quantidade de A\u00e7\u00f5es Preferenciais - Percentual": "97,63", "Total de A\u00e7\u00f5es - Quantidade": "634.204.716", "Total de A\u00e7\u00f5es - Percentual": "50,15"}}, "Composi\u00e7\u00e3o do Capital Social": {"date": "09/02/2024", "csv": {"Ordin\u00e1rias": "928.965.058", "Preferenciais": "335.747.796", "Total": "1.264.712.854"}}}, "hapv3.pdf": {"Dados da Companhia": {"csv": {"Nome de Preg\u00e3o:": "HAPVIDA", "C\u00f3digos de Negocia\u00e7\u00e3o:": "Mais C\u00f3digos\nHAPV3; HAPV99", "CNPJ:": "05.197.443/0001-38", "Atividade Principal:": "Participa\u00e7\u00e3o. Como S\u00f3cia Ou Acionista. em\nOutras Empresas. Predominantemente de\nAssist\u00eancia M\u00e9dica. Bem Como A\nRealiza\u00e7\u00e3o de Investimentos Diretos E A\nExplora\u00e7\u00e3o de Atividades de Presta\u00e7\u00e3o de\nServi\u00e7os", "Classi\u0000ca\u00e7\u00e3o Setorial:": "Sa\u00fade / Serv.M\u00e9d.Hospit..An\u00e1lises e\nDiagn\u00f3sticos / Serv.M\u00e9d.Hospit..An\u00e1lises e\nDiagn\u00f3sticos", "Site:": "www.hapvida.com.br\n(http://www.hapvida.com.br)"}}, "Dados Econ\u00f4mico-Financeiros - R$ - mil": {"Balan\u00e7o Patrimonial - Consolidado": {"csv": {"Ativo Imobilizado, Investimentos e Intang\u00edvel - Inicial": "59.061.848", "Ativo Imobilizado, Investimentos e Intang\u00edvel - Final": "58.208.836", "Ativo Total - Inicial": "73.213.730", "Ativo Total - Final": "74.771.863", "Patrim\u00f3nio L\u00edquido - Inicial": "48.756.711", "Patrim\u00f3nio L\u00edquido - Final": "49.123.078", "Patrim\u00f4nio L\u00edquido Atribu\u00eddo \u00e0 Controladora - Inicial": "48.749.437", "Patrim\u00f4nio L\u00edquido Atribu\u00eddo \u00e0 Controladora - Final": "49.114.428"}, "Inicio": "31/12/2022", "Fim": "30/09/2023"}, "Demonstra\u00e7\u00e3o do Resultado - Consolidado": {"csv": {"Receita de Venda - Inicial": "17.246.350", "Receita de Venda - Final": "20.447.881", "Resultado Bruto - Inicial": "4.149.893", "Resultado Bruto - Final": "5.072.501", "Resultado de Equival\u00eancia Patrimonial - Inicial": "0", "Resultado de Equival\u00eancia Patrimonial - Final": "0", "Resultado Financeiro - Inicial": "(776.208)", "Resultado Financeiro - Final": "(1.048.379)", "Resultado L\u00edquido das Opera\u00e7\u00f5es Continuadas - Inicial": "(459.168)", "Resultado L\u00edquido das Opera\u00e7\u00f5es Continuadas - Final": "(713.066)", "Lucro (Preju\u00edzo) do Per\u00edodo - Inicial": "(459.168)", "Lucro (Preju\u00edzo) do Per\u00edodo - Final": "(709.393)", "Lucro (Preju\u00edzo) do Per\u00edodo Atribu\u00eddo \u00e0 Controladora - Inicial": "(460.566)", "Lucro (Preju\u00edzo) do Per\u00edodo Atribu\u00eddo \u00e0 Controladora - Final": "(709.118)"}, "Inicio": "01/01/2022 a\n30/09/2022", "Fim": "01/01/2023 a\n30/09/2023"}, "Demonstra\u00e7\u00e3o do Fluxo de Caixa - Consolidado": {"csv": {"Atividades Operacionais - Inicial": "813.149", "Atividades Operacionais - Final": "1.809.501", "Atividades de Investimento - Inicial": "1.814.807", "Atividades de Investimento - Final": "(995.928)", "Atividades de Financiamento - Inicial": "(2.406.505)", "Atividades de Financiamento - Final": "(1.440.584)", "Varia\u00e7\u00e3o Cambial sobre Caixa e Equivalentes - Inicial": "0", "Varia\u00e7\u00e3o Cambial sobre Caixa e Equivalentes - Final": "0", "Aumento (Redu\u00e7\u00e3o) de Caixa e Equivalentes - Inicial": "221.451", "Aumento (Redu\u00e7\u00e3o) de Caixa e Equivalentes - Final": "(627.011)"}, "Inicio": "01/01/2022 a\n30/09/2022", "Fim": "01/01/2023 a\n30/09/2023"}}, "Posi\u00e7\u00e3o Acion\u00e1ria*": {"Ana Christina Fontoura Koren de Lima %ON": "0,53", "Ana Christina Fontoura Koren de Lima %PN": "0,00", "Ana Christina Fontoura Koren de Lima %TOTAL": "0,53", "Blackrock. Inc. %ON": "5,14", "Blackrock. Inc. %PN": "0,00", "Blackrock. Inc. %TOTAL": "5,14", "Candido Pinheiro Koren de Lima %ON": "0,55", "Candido Pinheiro Koren de Lima %PN": "0,00", "Candido Pinheiro Koren de Lima %TOTAL": "0,55", "Candido Pinheiro Koren de Lima Junior %ON": "0,45", "Candido Pinheiro Koren de Lima Junior %PN": "0,00", "Candido Pinheiro Koren de Lima Junior %TOTAL": "0,45", "Jorge Fontoura Pinheiro Koren de Lima %ON": "0,57", "Jorge Fontoura Pinheiro Koren de Lima %PN": "0,00", "Jorge Fontoura Pinheiro Koren de Lima %TOTAL": "0,57", "Ppar Pinheiro Participa\u00e7\u00f5es S.A. %ON": "33,89", "Ppar Pinheiro Participa\u00e7\u00f5es S.A. %PN": "0,00", "Ppar Pinheiro Participa\u00e7\u00f5es S.A. %TOTAL": "33,89", "Outros %ON": "58,29", "Outros %PN": "0,00", "Outros %TOTAL": "58,29", "A\u00e7\u00f5es Tesouraria %ON": "0,59", "A\u00e7\u00f5es Tesouraria %PN": "0,00", "A\u00e7\u00f5es Tesouraria %TOTAL": "0,59"}, "A\u00e7\u00f5es em Circula\u00e7\u00e3o no Mercado": {"date": "25/04/2022", "csv": {"Pessoas F\u00edsicas - Quantidade": "48.099", "Pessoas F\u00edsicas - Percentual": "-", "Pessoas Jur\u00eddicas - Quantidade": "300", "Pessoas Jur\u00eddicas - Percentual": "-", "Investidores Institucionais - Quantidade": "2.237", "Investidores Institucionais - Percentual": "-", "Quantidade de A\u00e7\u00f5es Ordin\u00e1rias - Quantidade": "4.455.957.762", "Quantidade de A\u00e7\u00f5es Ordin\u00e1rias - Percentual": "62,37", "Total de A\u00e7\u00f5es - Quantidade": "4.455.957.762", "Total de A\u00e7\u00f5es - Percentual": "62,37"}}, "Composi\u00e7\u00e3o do Capital Social": {"date": "12/04/2023", "csv": {"Ordin\u00e1rias": "7.539.463.263", "Preferenciais": "0", "Total": "7.539.463.263"}}}, "mglu3.pdf": {"Dados da Companhia": {"csv": {"Nome de Preg\u00e3o:": "MAGAZ LUIZA", "C\u00f3digos de Negocia\u00e7\u00e3o:": "Mais C\u00f3digos\nMGLU3", "CNPJ:": "47.960.950/0001-21", "Atividade Principal:": "Somos Uma Plataforma de Varejo\nMulticanal.", "Classi\u0000ca\u00e7\u00e3o Setorial:": "Consumo C\u00edclico / Com\u00e9rcio /\nEletrodom\u00e9sticos", "Site:": "www.magazineluiza.com.br\n(http://www.magazineluiza.com.br)"}}, "Dados Econ\u00f4mico-Financeiros - R$ - mil": {"Balan\u00e7o Patrimonial - Consolidado": {"csv": {"Ativo Imobilizado, Investimentos e Intang\u00edvel - Inicial": "10.233.319", "Ativo Imobilizado, Investimentos e Intang\u00edvel - Final": "9.998.927", "Ativo Total - Inicial": "38.098.122", "Ativo Total - Final": "36.918.960", "Patrim\u00f3nio L\u00edquido - Inicial": "9.726.584", "Patrim\u00f3nio L\u00edquido - Final": "9.532.654", "Patrim\u00f4nio L\u00edquido Atribu\u00eddo \u00e0 Controladora - Inicial": "9.726.584", "Patrim\u00f4nio L\u00edquido Atribu\u00eddo \u00e0 Controladora - Final": "9.532.654"}, "Inicio": "31/12/2022", "Fim": "30/09/2023"}, "Demonstra\u00e7\u00e3o do Resultado - Consolidado": {"csv": {"Receita de Venda - Inicial": "26.131.584", "Receita de Venda - Final": "26.218.408", "Resultado Bruto - Inicial": "7.033.035", "Resultado Bruto - Final": "7.697.584", "Resultado de Equival\u00eancia Patrimonial - Inicial": "(25.944)", "Resultado de Equival\u00eancia Patrimonial - Final": "(28.353)", "Resultado Financeiro - Inicial": "(1.472.233)", "Resultado Financeiro - Final": "(1.465.059)", "Resultado L\u00edquido das Opera\u00e7\u00f5es Continuadas - Inicial": "(665.131)", "Resultado L\u00edquido das Opera\u00e7\u00f5es Continuadas - Final": "(269.183)", "Lucro (Preju\u00edzo) do Per\u00edodo - Inicial": "(665.131)", "Lucro (Preju\u00edzo) do Per\u00edodo - Final": "(269.183)", "Lucro (Preju\u00edzo) do Per\u00edodo Atribu\u00eddo \u00e0 Controladora - Inicial": "(665.131)", "Lucro (Preju\u00edzo) do Per\u00edodo Atribu\u00eddo \u00e0 Controladora - Final": "(269.183)"}, "Inicio": "01/01/2022 a\n30/09/2022", "Fim": "01/01/2023 a\n30/09/2023"}, "Demonstra\u00e7\u00e3o do Fluxo de Caixa - Consolidado": {"csv": {"Atividades Operacionais - Inicial": "1.761.045", "Atividades Operacionais - Final": "2.597.830", "Atividades de Investimento - Inicial": "(1.090.468)", "Atividades de Investimento - Final": "(142.593)", "Atividades de Financiamento - Inicial": "(1.424.585)", "Atividades de Financiamento - Final": "(2.071.259)", "Varia\u00e7\u00e3o Cambial sobre Caixa e Equivalentes - Inicial": "0", "Varia\u00e7\u00e3o Cambial sobre Caixa e Equivalentes - Final": "0", "Aumento (Redu\u00e7\u00e3o) de Caixa e Equivalentes - Inicial": "(754.008)", "Aumento (Redu\u00e7\u00e3o) de Caixa e Equivalentes - Final": "383.978"}, "Inicio": "01/01/2022 a\n30/09/2022", "Fim": "01/01/2023 a\n30/09/2023"}}, "Posi\u00e7\u00e3o Acion\u00e1ria*": {"Fabr\u00edcio Bittar Garcia %ON": "0,11", "Fabr\u00edcio Bittar Garcia %PN": "0,00", "Fabr\u00edcio Bittar Garcia %TOTAL": "0,11", "Fernando Henrique Borges Trajano %ON": "0,32", "Fernando Henrique Borges Trajano %PN": "0,00", "Fernando Henrique Borges Trajano %TOTAL": "0,32", "Fl\u00e1via Bittar Garcia Faleiros %ON": "0,06", "Fl\u00e1via Bittar Garcia Faleiros %PN": "0,00", "Fl\u00e1via Bittar Garcia Faleiros %TOTAL": "0,06", "Franco Bittar Garcia %ON": "0,05", "Franco Bittar Garcia %PN": "0,00", "Franco Bittar Garcia %TOTAL": "0,05", "Ismael Borges Trajano %ON": "0,32", "Ismael Borges Trajano %PN": "0,00", "Ismael Borges Trajano %TOTAL": "0,32", "Ltd Administra\u00e7\u00e3o E Participa\u00e7\u00f5es S.A. %ON": "51,40", "Ltd Administra\u00e7\u00e3o E Participa\u00e7\u00f5es S.A. %PN": "0,00", "Ltd Administra\u00e7\u00e3o E Participa\u00e7\u00f5es S.A. %TOTAL": "51,40", "Luiza Helena Trajano In\u00e1cio Rodrigues %ON": "0,86", "Luiza Helena Trajano In\u00e1cio Rodrigues %PN": "0,00", "Luiza Helena Trajano In\u00e1cio Rodrigues %TOTAL": "0,86", "Wagner Garcia Participa\u00e7\u00f5es S.A. %ON": "3,09", "Wagner Garcia Participa\u00e7\u00f5es S.A. %PN": "0,00", "Wagner Garcia Participa\u00e7\u00f5es S.A. %TOTAL": "3,09", "Outros %ON": "42,75", "Outros %PN": "0,00", "Outros %TOTAL": "42,75", "A\u00e7\u00f5es Tesouraria %ON": "1,06", "A\u00e7\u00f5es Tesouraria %PN": "0,00", "A\u00e7\u00f5es Tesouraria %TOTAL": "1,06"}, "A\u00e7\u00f5es em Circula\u00e7\u00e3o no Mercado": {"date": "18/04/2022", "csv": {"Pessoas F\u00edsicas - Quantidade": "579.661", "Pessoas F\u00edsicas - Percentual": "-", "Pessoas Jur\u00eddicas - Quantidade": "2.405", "Pessoas Jur\u00eddicas - Percentual": "-", "Investidores Institucionais - Quantidade": "924", "Investidores Institucionais - Percentual": "-", "Quantidade de A\u00e7\u00f5es Ordin\u00e1rias - Quantidade": "2.874.188.573", "Quantidade de A\u00e7\u00f5es Ordin\u00e1rias - Percentual": "42,59", "Total de A\u00e7\u00f5es - Quantidade": "2.874.188.573", "Total de A\u00e7\u00f5es - Percentual": "42,59"}}, "Composi\u00e7\u00e3o do Capital Social": {"date": "26/08/2021", "csv": {"Ordin\u00e1rias": "6.748.926.848", "Preferenciais": "0", "Total": "6.748.926.848"}}}, "abev3.pdf": {"Dados da Companhia": {"csv": {"Nome de Preg\u00e3o:": "AMBEV S/A", "C\u00f3digos de Negocia\u00e7\u00e3o:": "Mais C\u00f3digos\nABEV3", "CNPJ:": "07.526.557/0001-00", "Atividade Principal:": "Fabrica\u00e7\u00e3o E Distribui\u00e7\u00e3o de Cervejas.\nRefrigerantes E Bebidas N\u00e3o Carbonatadas\nE N\u00e3o Alco\u00f3licas.", "Classi\u0000ca\u00e7\u00e3o Setorial:": "Consumo n\u00e3o C\u00edclico / Bebidas / Cervejas e\nRefrigerantes", "Site:": "http://ri.ambev.com.br\n(http://http://ri.ambev.com.br)"}}, "Dados Econ\u00f4mico-Financeiros - R$ - mil": {"Balan\u00e7o Patrimonial - Consolidado": {"csv": {"Ativo Imobilizado, Investimentos e Intang\u00edvel - Inicial": "80.203.916", "Ativo Imobilizado, Investimentos e Intang\u00edvel - Final": "74.964.592", "Ativo Total - Inicial": "137.958.083", "Ativo Total - Final": "132.644.133", "Patrim\u00f4nio L\u00edquido - Inicial": "83.327.827", "Patrim\u00f4nio L\u00edquido - Final": "80.143.802", "Patrim\u00f4nio L\u00edquido Atribu\u00eddo \u00e0 Controladora - Inicial": "81.955.633", "Patrim\u00f4nio L\u00edquido Atribu\u00eddo \u00e0 Controladora - Final": "78.969.290"}, "Inicio": "31/12/2022", "Fim": "31/12/2023"}, "Demonstra\u00e7\u00e3o do Resultado - Consolidado": {"csv": {"Receita de Venda - Inicial": "79.708.827", "Receita de Venda - Final": "79.736.856", "Resultado Bruto - Inicial": "39.286.758", "Resultado Bruto - Final": "40.445.285", "Resultado de Equival\u00eancia Patrimonial - Inicial": "(29.106)", "Resultado de Equival\u00eancia Patrimonial - Final": "(185.406)", "Resultado Financeiro - Inicial": "(3.423.170)", "Resultado Financeiro - Final": "(3.609.752)", "Resultado L\u00edquido das Opera\u00e7\u00f5es Continuadas - Inicial": "14.891.291", "Resultado L\u00edquido das Opera\u00e7\u00f5es Continuadas - Final": "14.960.459", "Lucro (Preju\u00edzo) do Per\u00edodo - Inicial": "14.891.291", "Lucro (Preju\u00edzo) do Per\u00edodo - Final": "14.960.459", "Lucro (Preju\u00edzo) do Per\u00edodo Atribu\u00eddo \u00e0 Controladora - Inicial": "14.457.943", "Lucro (Preju\u00edzo) do Per\u00edodo Atribu\u00eddo \u00e0 Controladora - Final": "14.501.944"}, "Inicio": "01/01/2022 a\n31/12/2022", "Fim": "01/01/2023 a\n31/12/2023"}, "Demonstra\u00e7\u00e3o do Fluxo de Caixa - Consolidado": {"csv": {"Atividades Operacionais - Inicial": "20.642.153", "Atividades Operacionais - Final": "24.711.429", "Atividades de Investimento - Inicial": "(5.004.139)", "Atividades de Investimento - Final": "(5.765.984)", "Atividades de Financiamento - Inicial": "(16.337.906)", "Atividades de Financiamento - Final": "(16.115.207)", "Varia\u00e7\u00e3o Cambial sobre Caixa e Equivalentes - Inicial": "(1.045.200)", "Varia\u00e7\u00e3o Cambial sobre Caixa e Equivalentes - Final": "(1.623.327)", "Aumento (Redu\u00e7\u00e3o) de Caixa e Equivalentes - Inicial": "(1.745.092)", "Aumento (Redu\u00e7\u00e3o) de Caixa e Equivalentes - Final": "1.206.911"}, "Inicio": "01/01/2022 a\n31/12/2022", "Fim": "01/01/2023 a\n31/12/2023"}}, "Posi\u00e7\u00e3o Acion\u00e1ria*": {"Ambrew S.\u00e0.r.l %ON": "8,17", "Ambrew S.\u00e0.r.l %PN": "0,00", "Ambrew S.\u00e0.r.l %TOTAL": "8,17", "Funda\u00e7\u00e3o Zerrenner %ON": "10,22", "Funda\u00e7\u00e3o Zerrenner %PN": "0,00", "Funda\u00e7\u00e3o Zerrenner %TOTAL": "10,22", "Interbrew International Bv %ON": "53,59", "Interbrew International Bv %PN": "0,00", "Interbrew International Bv %TOTAL": "53,59", "Outros %ON": "27,98", "Outros %PN": "0,00", "Outros %TOTAL": "27,98", "A\u00e7\u00f5es Tesouraria %ON": "0,04", "A\u00e7\u00f5es Tesouraria %PN": "0,00", "A\u00e7\u00f5es Tesouraria %TOTAL": "0,04"}, "A\u00e7\u00f5es em Circula\u00e7\u00e3o no Mercado": {"date": "28/04/2023", "csv": {"Pessoas F\u00edsicas - Quantidade": "308.094", "Pessoas F\u00edsicas - Percentual": "-", "Pessoas Jur\u00eddicas - Quantidade": "1.897", "Pessoas Jur\u00eddicas - Percentual": "-", "Investidores Institucionais - Quantidade": "652", "Investidores Institucionais - Percentual": "-", "Quantidade de A\u00e7\u00f5es Ordin\u00e1rias - Quantidade": "4.394.245.879", "Quantidade de A\u00e7\u00f5es Ordin\u00e1rias - Percentual": "27,89", "Total de A\u00e7\u00f5es - Quantidade": "4.394.245.879", "Total de A\u00e7\u00f5es - Percentual": "27,89"}}, "Composi\u00e7\u00e3o do Capital Social": {"date": "25/04/2023", "csv": {"Ordin\u00e1rias": "15.753.833.284", "Preferenciais": "0", "Total": "15.753.833.284"}}}, "vale3.pdf": {"Dados da Companhia": {"csv": {"Nome de Preg\u00e3o:": "VALE", "C\u00f3digos de Negocia\u00e7\u00e3o:": "Mais C\u00f3digos\nVALE3", "CNPJ:": "33.592.510/0001-54", "Atividade Principal:": "Minera\u00e7\u00e3o", "Classi\u0000ca\u00e7\u00e3o Setorial:": "Materiais B\u00e1sicos / Minera\u00e7\u00e3o / Minerais\nMet\u00e1licos"}}, "Dados Econ\u00f4mico-Financeiros - R$ - mil": {"Balan\u00e7o Patrimonial - Consolidado": {"csv": {"Ativo Imobilizado, Investimentos e Intang\u00edvel - Inicial": "297.274.000", "Ativo Imobilizado, Investimentos e Intang\u00edvel - Final": "299.672.000", "Ativo Total - Inicial": "453.387.000", "Ativo Total - Final": "455.984.000", "Patrim\u00f4nio L\u00edquido - Inicial": "194.894.000", "Patrim\u00f4nio L\u00edquido - Final": "198.325.000", "Patrim\u00f4nio L\u00edquido Atribu\u00eddo \u00e0 Controladora - Inicial": "187.112.000", "Patrim\u00f4nio L\u00edquido Atribu\u00eddo \u00e0 Controladora - Final": "190.965.000"}, "Inicio": "31/12/2022", "Fim": "31/12/2023"}, "Demonstra\u00e7\u00e3o do Resultado - Consolidado": {"csv": {"Receita de Venda - Inicial": "226.508.000", "Receita de Venda - Final": "208.066.000", "Resultado Bruto - Inicial": "102.313.000", "Resultado Bruto - Final": "88.050.000", "Resultado de Equival\u00eancia Patrimonial - Inicial": "1.616.000", "Resultado de Equival\u00eancia Patrimonial - Final": "(5.434.000)", "Resultado Financeiro - Inicial": "11.378.000", "Resultado Financeiro - Final": "(9.718.000)", "Resultado L\u00edquido das Opera\u00e7\u00f5es Continuadas - Inicial": "86.519.000", "Resultado L\u00edquido das Opera\u00e7\u00f5es Continuadas - Final": "40.554.000", "Lucro (Preju\u00edzo) do Per\u00edodo - Inicial": "96.337.000", "Lucro (Preju\u00edzo) do Per\u00edodo - Final": "40.554.000", "Lucro (Preju\u00edzo) do Per\u00edodo Atribu\u00eddo \u00e0 Controladora - Inicial": "95.924.000", "Lucro (Preju\u00edzo) do Per\u00edodo Atribu\u00eddo \u00e0 Controladora - Final": "39.940.000"}, "Inicio": "01/01/2022 a\n31/12/2022", "Fim": "01/01/2023 a\n31/12/2023"}, "Demonstra\u00e7\u00e3o do Fluxo de Caixa - Consolidado": {"csv": {"Atividades Operacionais - Inicial": "58.201.000", "Atividades Operacionais - Final": "65.905.000", "Atividades de Investimento - Inicial": "(24.176.000)", "Atividades de Investimento - Final": "(31.425.000)", "Demonstra\u00e7\u00e3o do Fluxo de Caixa - Inicial": "Consolidado", "Demonstra\u00e7\u00e3o do Fluxo de Caixa - Final": "-", "Atividades de Financiamento - Inicial": "(71.005.000)", "Atividades de Financiamento - Final": "(37.002.000)", "Varia\u00e7\u00e3o Cambial sobre Caixa e Equivalentes - Inicial": "(3.718.000)", "Varia\u00e7\u00e3o Cambial sobre Caixa e Equivalentes - Final": "(4.715.000)", "Aumento (Redu\u00e7\u00e3o) de Caixa e Equivalentes - Inicial": "(40.698.000)", "Aumento (Redu\u00e7\u00e3o) de Caixa e Equivalentes - Final": "(7.237.000)"}, "Inicio": "01/01/2022 a\n31/12/2022", "Fim": "01/01/2023 a\n31/12/2023"}}, "Posi\u00e7\u00e3o Acion\u00e1ria*": {"Blackrock. Inc. %ON": "6,12", "Blackrock. Inc. %PN": "0,00", "Blackrock. Inc. %TOTAL": "6,12", "Caixa de Previd\u00eancia Dos Funcion\u00e1rios Do Banco Do Brasil (cid:0) Previ %ON": "8,68", "Caixa de Previd\u00eancia Dos Funcion\u00e1rios Do Banco Do Brasil (cid:0) Previ %PN": "0,00", "Caixa de Previd\u00eancia Dos Funcion\u00e1rios Do Banco Do Brasil (cid:0) Previ %TOTAL": "8,68", "Governo Federal %ON": "0,00", "Governo Federal %PN": "100,00", "Governo Federal %TOTAL": "0,00", "Mitsui Amp; Co.. Ltd %ON": "6,31", "Mitsui Amp; Co.. Ltd %PN": "0,00", "Mitsui Amp; Co.. Ltd %TOTAL": "6,31", "Outros %ON": "76,48", "Outros %PN": "0,00", "Outros %TOTAL": "76,48", "A\u00e7\u00f5es Tesouraria %ON": "2,41", "A\u00e7\u00f5es Tesouraria %PN": "0,00", "A\u00e7\u00f5es Tesouraria %TOTAL": "2,41"}, "A\u00e7\u00f5es em Circula\u00e7\u00e3o no Mercado": {"date": "29/04/2022", "csv": {"Pessoas F\u00edsicas - Quantidade": "510.874", "Pessoas F\u00edsicas - Percentual": "-", "Pessoas Jur\u00eddicas - Quantidade": "13.871", "Pessoas Jur\u00eddicas - Percentual": "-", "Investidores Institucionais - Quantidade": "2.342", "Investidores Institucionais - Percentual": "-", "Quantidade de A\u00e7\u00f5es Ordin\u00e1rias - Quantidade": "4.448.529.763", "Quantidade de A\u00e7\u00f5es Ordin\u00e1rias - Percentual": "98,01", "Total de A\u00e7\u00f5es - Quantidade": "4.448.529.763", "Total de A\u00e7\u00f5es - Percentual": "98,01"}}, "Composi\u00e7\u00e3o do Capital Social": {"date": "02/03/2023", "csv": {"Ordin\u00e1rias": "4.539.007.568", "-": "02/03/2023", "Preferenciais": "12", "Total": "4.539.007.580"}}}, "vamo3.pdf": {"Dados da Companhia": {"csv": {"Nome de Preg\u00e3o:": "VAMOS", "C\u00f3digos de Negocia\u00e7\u00e3o:": "Mais C\u00f3digos\nVAMO3", "CNPJ:": "23.373.000/0001-32", "Atividade Principal:": "Loca\u00e7\u00e3o E Venda de Caminh\u00f5es. M\u00e1quinas\nE Equipamentos Pesados E A Presta\u00e7\u00e3o de\nServi\u00e7os de Manuten\u00e7\u00e3o de Frota. Tanto\nPreventiva. Quanto Corretiva.", "Classi\u0000ca\u00e7\u00e3o Setorial:": "Consumo C\u00edclico / Diversos / Aluguel de\ncarros", "Site:": "http://www.grupovamos.com.br/\n(http://http://www.grupovamos.com.br/)"}}, "Dados Econ\u00f4mico-Financeiros - R$ - mil": {"Balan\u00e7o Patrimonial - Consolidado": {"csv": {"Ativo Imobilizado, Investimentos e Intang\u00edvel - Inicial": "12.250.835", "Ativo Imobilizado, Investimentos e Intang\u00edvel - Final": "13.271.083", "Ativo Total - Inicial": "16.675.416", "Ativo Total - Final": "19.219.164", "Patrim\u00f3nio L\u00edquido - Inicial": "3.638.888", "Patrim\u00f3nio L\u00edquido - Final": "4.878.781", "Patrim\u00f4nio L\u00edquido Atribu\u00eddo \u00e0 Controladora - Inicial": "3.638.888", "Patrim\u00f4nio L\u00edquido Atribu\u00eddo \u00e0 Controladora - Final": "4.878.781"}, "Inicio": "31/12/2022", "Fim": "30/09/2023"}, "Demonstra\u00e7\u00e3o do Resultado - Consolidado": {"csv": {"Receita de Venda - Inicial": "3.522.021", "Receita de Venda - Final": "4.632.745", "Resultado Bruto - Inicial": "1.470.709", "Resultado Bruto - Final": "2.053.244", "Resultado de Equival\u00eancia Patrimonial - Inicial": "0", "Resultado de Equival\u00eancia Patrimonial - Final": "0", "Resultado Financeiro - Inicial": "(549.810)", "Resultado Financeiro - Final": "(1.178.667)", "Resultado L\u00edquido das Opera\u00e7\u00f5es Continuadas - Inicial": "414.354", "Resultado L\u00edquido das Opera\u00e7\u00f5es Continuadas - Final": "391.527", "Lucro (Preju\u00edzo) do Per\u00edodo - Inicial": "414.354", "Lucro (Preju\u00edzo) do Per\u00edodo - Final": "391.527", "Lucro (Preju\u00edzo) do Per\u00edodo Atribu\u00eddo \u00e0 Controladora - Inicial": "414.354", "Lucro (Preju\u00edzo) do Per\u00edodo Atribu\u00eddo \u00e0 Controladora - Final": "391.527"}, "Inicio": "01/01/2022 a\n30/09/2022", "Fim": "01/01/2023 a\n30/09/2023"}, "Demonstra\u00e7\u00e3o do Fluxo de Caixa - Consolidado": {"csv": {"Atividades Operacionais - Inicial": "(2.715.876)", "Atividades Operacionais - Final": "(1.683.442)", "Atividades de Investimento - Inicial": "(127.105)", "Atividades de Investimento - Final": "(279.335)", "Atividades de Financiamento - Inicial": "2.773.527", "Atividades de Financiamento - Final": "2.263.417", "Varia\u00e7\u00e3o Cambial sobre Caixa e Equivalentes - Inicial": "0", "Varia\u00e7\u00e3o Cambial sobre Caixa e Equivalentes - Final": "0", "Aumento (Redu\u00e7\u00e3o) de Caixa e Equivalentes - Inicial": "(69.454)", "Aumento (Redu\u00e7\u00e3o) de Caixa e Equivalentes - Final": "300.640"}, "Inicio": "01/01/2022 a\n30/09/2022", "Fim": "01/01/2023 a\n30/09/2023"}}, "Posi\u00e7\u00e3o Acion\u00e1ria*": {"Simpar S.A. %ON": "54,82", "Simpar S.A. %PN": "0,00", "Simpar S.A. %TOTAL": "54,82", "Outros %ON": "44,47", "Outros %PN": "0,00", "Outros %TOTAL": "44,47", "A\u00e7\u00f5es Tesouraria %ON": "0,72", "A\u00e7\u00f5es Tesouraria %PN": "0,00", "A\u00e7\u00f5es Tesouraria %TOTAL": "0,72"}, "A\u00e7\u00f5es em Circula\u00e7\u00e3o no Mercado": {"date": "28/04/2022", "csv": {"Pessoas F\u00edsicas - Quantidade": "7", "Pessoas F\u00edsicas - Percentual": "-", "Pessoas Jur\u00eddicas - Quantidade": "501", "Pessoas Jur\u00eddicas - Percentual": "-", "Investidores Institucionais - Quantidade": "1.207", "Investidores Institucionais - Percentual": "-", "Quantidade de A\u00e7\u00f5es Ordin\u00e1rias - Quantidade": "314.724.970", "Quantidade de A\u00e7\u00f5es Ordin\u00e1rias - Percentual": "30,69", "Total de A\u00e7\u00f5es - Quantidade": "314.724.970", "Total de A\u00e7\u00f5es - Percentual": "30,69"}}, "Composi\u00e7\u00e3o do Capital Social": {"date": "29/06/2023", "csv": {"Ordin\u00e1rias": "1.104.324.569", "Preferenciais": "0", "Total": "1.104.324.569"}}}, "bbdc4.pdf": {"Dados da Companhia": {"csv": {"Nome de Preg\u00e3o:": "BRADESCO", "C\u00f3digos de Negocia\u00e7\u00e3o:": "Mais C\u00f3digos\nBBDC3; BBDC4", "CNPJ:": "60.746.948/0001-12", "Atividade Principal:": "Pr\u00e1tica de Opera\u00e7\u00f5es Banc\u00e1rias em Geral.\nInclusive C\u00e2mbio", "Classi\u0000ca\u00e7\u00e3o Setorial:": "Financeiro / Intermedi\u00e1rios Financeiros /\nBancos", "Site:": "www.bradesco.com.br\n(http://www.bradesco.com.br)"}}, "Dados Econ\u00f4mico-Financeiros - R$ - mil": {"Balan\u00e7o Patrimonial - Consolidado": {"csv": {"Ativo Imobilizado, Investimentos e Intang\u00edvel - Inicial": "30.770.935", "Ativo Imobilizado, Investimentos e Intang\u00edvel - Final": "33.225.155", "Ativo Total - Inicial": "1.792.288.792", "Ativo Total - Final": "1.927.523.249", "Patrim\u00f4nio L\u00edquido - Inicial": "154.263.223", "Patrim\u00f4nio L\u00edquido - Final": "161.182.449"}, "Inicio": "31/12/2022", "Fim": "31/12/2023"}, "Demonstra\u00e7\u00e3o do Resultado - Consolidado": {"csv": {"Receita da Intermedia\u00e7\u00e3o Financeira - Inicial": "205.913.274", "Receita da Intermedia\u00e7\u00e3o Financeira - Final": "224.457.793", "Resultado Bruto da Intermedia\u00e7\u00e3o Financeira - Inicial": "75.111.361", "Resultado Bruto da Intermedia\u00e7\u00e3o Financeira - Final": "68.081.738", "Resultado de Equival\u00eancia Patrimonial - Inicial": "(55.418.959)", "Resultado de Equival\u00eancia Patrimonial - Final": "(61.623.067)", "Lucro (Preju\u00edzo) do Per\u00edodo - Inicial": "20.732.172", "Lucro (Preju\u00edzo) do Per\u00edodo - Final": "15.121.802"}, "Inicio": "01/01/2022 a\n31/12/2022", "Fim": "01/01/2023 a\n31/12/2023"}, "Demonstra\u00e7\u00e3o do Fluxo de Caixa - Consolidado": {"csv": {"Atividades Operacionais - Inicial": "49.767.703", "Atividades Operacionais - Final": "(177.628)", "Atividades de Investimento - Inicial": "(17.778.682)", "Atividades de Investimento - Final": "83.606.232", "Atividades de Financiamento - Inicial": "21.917.788", "Atividades de Financiamento - Final": "(23.062.770)", "Varia\u00e7\u00e3o Cambial sobre Caixa e Equivalentes - Inicial": "892.293", "Varia\u00e7\u00e3o Cambial sobre Caixa e Equivalentes - Final": "239.325", "Aumento (Redu\u00e7\u00e3o) de Caixa e Equivalentes - Inicial": "54.799.102", "Aumento (Redu\u00e7\u00e3o) de Caixa e Equivalentes - Final": "60.605.159"}, "Inicio": "01/01/2022 a\n31/12/2022", "Fim": "01/01/2023 a\n31/12/2023"}}, "Posi\u00e7\u00e3o Acion\u00e1ria*": {"Cidade de Deus Cia Cial Participa\u00e7\u00f5es %ON": "45,87", "Cidade de Deus Cia Cial Participa\u00e7\u00f5es %PN": "0,02", "Cidade de Deus Cia Cial Participa\u00e7\u00f5es %TOTAL": "22,99", "Funda\u00e7\u00e3o Bradesco %ON": "17,16", "Funda\u00e7\u00e3o Bradesco %PN": "0,00", "Funda\u00e7\u00e3o Bradesco %TOTAL": "8,59", "Ncf Participa\u00e7\u00f5es S.A. %ON": "8,48", "Ncf Participa\u00e7\u00f5es S.A. %PN": "2,26", "Ncf Participa\u00e7\u00f5es S.A. %TOTAL": "5,37", "Outros %ON": "28,27", "Outros %PN": "97,52", "Outros %TOTAL": "62,84", "A\u00e7\u00f5es Tesouraria %ON": "0,23", "A\u00e7\u00f5es Tesouraria %PN": "0,20", "A\u00e7\u00f5es Tesouraria %TOTAL": "0,21"}, "A\u00e7\u00f5es em Circula\u00e7\u00e3o no Mercado": {"date": "27/12/2022", "csv": {"Pessoas F\u00edsicas - Quantidade": "798.152", "Pessoas F\u00edsicas - Percentual": "-", "Pessoas Jur\u00eddicas - Quantidade": "35.088", "Pessoas Jur\u00eddicas - Percentual": "-", "Investidores Institucionais - Quantidade": "1.223", "Investidores Institucionais - Percentual": "-", "Quantidade de A\u00e7\u00f5es Ordin\u00e1rias - Quantidade": "1.500.631.902", "Quantidade de A\u00e7\u00f5es Ordin\u00e1rias - Percentual": "28,11", "Quantidade de A\u00e7\u00f5es Preferenciais - Quantidade": "5.146.612.491", "Quantidade de A\u00e7\u00f5es Preferenciais - Percentual": "96,74", "Total de A\u00e7\u00f5es - Quantidade": "6.647.244.393", "Total de A\u00e7\u00f5es - Percentual": "62,37"}}, "Composi\u00e7\u00e3o do Capital Social": {"date": "10/03/2023", "csv": {"Ordin\u00e1rias": "5.330.304.681", "Preferenciais": "5.311.865.547", "Total": "10.642.170.228"}}}, "brkm5.pdf": {"Dados da Companhia": {"csv": {"Nome de Preg\u00e3o:": "BRASKEM", "C\u00f3digos de Negocia\u00e7\u00e3o:": "Mais C\u00f3digos\nBRKM3; BRKM5; BRKM6", "CNPJ:": "42.150.391/0001-70", "Atividade Principal:": "Produ\u00e7\u00e3o de Produtos Qu\u00edmicos. Utilidades.\nEnergia El\u00e9trica E Outros;presta\u00e7\u00e3o de\nServi\u00e7os Industriais;participa\u00e7\u00e3o em Outras\nSociedades;loca\u00e7\u00e3o de Bens;\nRepresenta\u00e7\u00e3o/consigna\u00e7\u00e3o de Produtos\nQu\u00edmicos", "Classi\u0000ca\u00e7\u00e3o Setorial:": "Materiais B\u00e1sicos / Qu\u00edmicos /\nPetroqu\u00edmicos", "Site:": "www.braskem.com.br\n(http://www.braskem.com.br)"}}, "Dados Econ\u00f4mico-Financeiros - R$ - mil": {"Balan\u00e7o Patrimonial - Consolidado": {"csv": {"Ativo Imobilizado, Investimentos e Intang\u00edvel - Inicial": "44.887.449", "Ativo Imobilizado, Investimentos e Intang\u00edvel - Final": "45.391.089", "Ativo Total - Inicial": "88.048.858", "Ativo Total - Final": "92.015.333", "Patrim\u00f3nio L\u00edquido - Inicial": "6.108.217", "Patrim\u00f3nio L\u00edquido - Final": "4.378.023", "Patrim\u00f4nio L\u00edquido Atribu\u00eddo \u00e0 Controladora - Inicial": "7.321.799", "Patrim\u00f4nio L\u00edquido Atribu\u00eddo \u00e0 Controladora - Final": "5.022.596"}, "Inicio": "31/12/2022", "Fim": "30/09/2023"}, "Demonstra\u00e7\u00e3o do Resultado - Consolidado": {"csv": {"Receita de Venda - Inicial": "77.529.527", "Receita de Venda - Final": "53.877.726", "Resultado Bruto - Inicial": "11.437.044", "Resultado Bruto - Final": "2.012.518", "Resultado de Equival\u00eancia Patrimonial - Inicial": "26.307", "Resultado de Equival\u00eancia Patrimonial - Final": "7.952", "Resultado Financeiro - Inicial": "(3.840.865)", "Resultado Financeiro - Final": "(2.601.325)", "Resultado L\u00edquido das Opera\u00e7\u00f5es Continuadas - Inicial": "1.062.888", "Resultado L\u00edquido das Opera\u00e7\u00f5es Continuadas - Final": "(3.138.992)", "Lucro (Preju\u00edzo) do Per\u00edodo - Inicial": "1.062.888", "Lucro (Preju\u00edzo) do Per\u00edodo - Final": "(3.138.992)", "Lucro (Preju\u00edzo) do Per\u00edodo Atribu\u00eddo \u00e0 Controladora - Inicial": "1.374.797", "Lucro (Preju\u00edzo) do Per\u00edodo Atribu\u00eddo \u00e0 Controladora - Final": "(3.004.369)"}, "Inicio": "01/01/2022 a\n30/09/2022", "Fim": "01/01/2023 a\n30/09/2023"}, "Demonstra\u00e7\u00e3o do Fluxo de Caixa - Consolidado": {"csv": {"Atividades Operacionais - Inicial": "6.640.981", "Atividades Operacionais - Final": "(3.286.005)", "Atividades de Investimento - Inicial": "(3.410.710)", "Atividades de Investimento - Final": "(3.016.941)", "Demonstra\u00e7\u00e3o do Fluxo de Caixa - Inicial": "Consolidado", "Demonstra\u00e7\u00e3o do Fluxo de Caixa - Final": "-", "Atividades de Financiamento - Inicial": "79.419", "Atividades de Financiamento - Final": "7.714.353", "Varia\u00e7\u00e3o Cambial sobre Caixa e Equivalentes - Inicial": "(253.216)", "Varia\u00e7\u00e3o Cambial sobre Caixa e Equivalentes - Final": "(241.042)", "Aumento (Redu\u00e7\u00e3o) de Caixa e Equivalentes - Inicial": "3.056.474", "Aumento (Redu\u00e7\u00e3o) de Caixa e Equivalentes - Final": "1.170.365"}, "Inicio": "01/01/2022 a\n30/09/2022", "Fim": "01/01/2023 a\n30/09/2023"}}, "Posi\u00e7\u00e3o Acion\u00e1ria*": {"Adr's %ON": "0,00", "Adr's %PN": "16,22", "Adr's %TOTAL": "7,03", "Norges Bank %ON": "0,00", "Norges Bank %PN": "4,91", "Norges Bank %TOTAL": "2,13", "Novonor S.A. - em Recupera\u00e7\u00e3o Judicial %ON": "0,00", "Novonor S.A. - em Recupera\u00e7\u00e3o Judicial %PN": "0,00", "Novonor S.A. - em Recupera\u00e7\u00e3o Judicial %TOTAL": "0,00", "Nsp Investimentos S.A. - em Recupera\u00e7\u00e3o Judicial %ON": "50,11", "Nsp Investimentos S.A. - em Recupera\u00e7\u00e3o Judicial %PN": "22,92", "Nsp Investimentos S.A. - em Recupera\u00e7\u00e3o Judicial %TOTAL": "38,32", "Petr\u00f3leo Brasileiro S.A. - Petrobras %ON": "47,03", "Petr\u00f3leo Brasileiro S.A. - Petrobras %PN": "21,93", "Petr\u00f3leo Brasileiro S.A. - Petrobras %TOTAL": "36,15", "Outros %ON": "2,86", "Outros %PN": "34,03", "Outros %TOTAL": "16,37", "A\u00e7\u00f5es Tesouraria %ON": "0,00", "A\u00e7\u00f5es Tesouraria %PN": "0,00", "A\u00e7\u00f5es Tesouraria %TOTAL": "0,00"}, "A\u00e7\u00f5es em Circula\u00e7\u00e3o no Mercado": {"date": "19/04/2022", "csv": {"Pessoas F\u00edsicas - Quantidade": "49.621", "Pessoas F\u00edsicas - Percentual": "-", "Pessoas Jur\u00eddicas - Quantidade": "3.630", "Pessoas Jur\u00eddicas - Percentual": "-", "Investidores Institucionais - Quantidade": "373", "Investidores Institucionais - Percentual": "-", "Quantidade de A\u00e7\u00f5es Ordin\u00e1rias - Quantidade": "12.907.077", "Quantidade de A\u00e7\u00f5es Ordin\u00e1rias - Percentual": "2,86", "Quantidade de A\u00e7\u00f5es Preferenciais - Quantidade": "265.691.276", "Quantidade de A\u00e7\u00f5es Preferenciais - Percentual": "77,00", "Total de A\u00e7\u00f5es - Quantidade": "278.598.353", "Total de A\u00e7\u00f5es - Percentual": "34,95"}}, "Composi\u00e7\u00e3o do Capital Social": {"date": "18/02/2022", "csv": {"Ordin\u00e1rias": "451.668.652", "Preferenciais": "345.539.182", "Total": "797.207.834"}}}, "elet3.pdf": {"Dados da Companhia": {"csv": {"Nome de Preg\u00e3o:": "ELETROBRAS", "C\u00f3digos de Negocia\u00e7\u00e3o:": "Mais C\u00f3digos\nELET3; ELET5; ELET6", "CNPJ:": "00.001.180/0001-26", "Atividade Principal:": "Empresa Holding de Gera\u00e7\u00e3o. Transmiss\u00e3o\nde Energia", "Classi\u0000ca\u00e7\u00e3o Setorial:": "Utilidade P\u00fablica / Energia El\u00e9trica /\nEnergia El\u00e9trica", "Site:": "www.eletrobras.com\n(http://www.eletrobras.com)"}}, "Dados Econ\u00f4mico-Financeiros - R$ - mil": {"Balan\u00e7o Patrimonial - Consolidado": {"csv": {"Ativo Imobilizado, Investimentos e Intang\u00edvel - Inicial": "148.705.808", "Ativo Imobilizado, Investimentos e Intang\u00edvel - Final": "148.876.345", "Ativo Total - Inicial": "270.217.462", "Ativo Total - Final": "267.057.654", "Patrim\u00f4nio L\u00edquido - Inicial": "111.028.636", "Patrim\u00f4nio L\u00edquido - Final": "112.464.644", "Patrim\u00f4nio L\u00edquido Atribu\u00eddo \u00e0 Controladora - Inicial": "110.504.796", "Patrim\u00f4nio L\u00edquido Atribu\u00eddo \u00e0 Controladora - Final": "112.333.372"}, "Inicio": "31/12/2022", "Fim": "31/12/2023"}, "Demonstra\u00e7\u00e3o do Resultado - Consolidado": {"csv": {"Receita de Venda - Inicial": "34.074.233", "Receita de Venda - Final": "37.158.908", "Resultado Bruto - Inicial": "18.216.623", "Resultado Bruto - Final": "18.485.409", "Resultado de Equival\u00eancia Patrimonial - Inicial": "2.369.777", "Resultado de Equival\u00eancia Patrimonial - Final": "2.062.090", "Resultado Financeiro - Inicial": "(4.373.595)", "Resultado Financeiro - Final": "(12.002.121)", "Resultado L\u00edquido das Opera\u00e7\u00f5es Continuadas - Inicial": "2.651.597", "Resultado L\u00edquido das Opera\u00e7\u00f5es Continuadas - Final": "4.726.875", "Lucro (Preju\u00edzo) do Per\u00edodo - Inicial": "3.638.382", "Lucro (Preju\u00edzo) do Per\u00edodo - Final": "4.394.861", "Lucro (Preju\u00edzo) do Per\u00edodo Atribu\u00eddo \u00e0 Controladora - Inicial": "3.635.377", "Lucro (Preju\u00edzo) do Per\u00edodo Atribu\u00eddo \u00e0 Controladora - Final": "4.549.774"}, "Inicio": "01/01/2022 a\n31/12/2022", "Fim": "01/01/2023 a\n31/12/2023"}, "Demonstra\u00e7\u00e3o do Fluxo de Caixa - Consolidado": {"csv": {"Atividades Operacionais - Inicial": "4.799.820", "Atividades Operacionais - Final": "8.242.958", "Atividades de Investimento - Inicial": "(24.325.739)", "Atividades de Investimento - Final": "819.418", "Atividades de Financiamento - Inicial": "30.072.386", "Atividades de Financiamento - Final": "(6.755.131)", "Varia\u00e7\u00e3o Cambial sobre Caixa e Equivalentes - Inicial": "0", "Varia\u00e7\u00e3o Cambial sobre Caixa e Equivalentes - Final": "0", "Aumento (Redu\u00e7\u00e3o) de Caixa e Equivalentes - Inicial": "10.546.467", "Aumento (Redu\u00e7\u00e3o) de Caixa e Equivalentes - Final": "2.307.245"}, "Inicio": "01/01/2022 a\n31/12/2022", "Fim": "01/01/2023 a\n31/12/2023"}}, "Posi\u00e7\u00e3o Acion\u00e1ria*": {"3g Radar Gestora de Recursos Ltda. %ON": "0,02", "3g Radar Gestora de Recursos Ltda. %PN": "10,80", "3g Radar Gestora de Recursos Ltda. %TOTAL": "1,33", "Banco Do Nordeste %ON": "0,06", "Banco Do Nordeste %PN": "0,00", "Banco Do Nordeste %TOTAL": "0,05", "Banco Nacional de Desenvolvimento Econ\u00f4mico E Social (cid:0) Bndes %ON": "3,68", "Banco Nacional de Desenvolvimento Econ\u00f4mico E Social (cid:0) Bndes %PN": "6,52", "Banco Nacional de Desenvolvimento Econ\u00f4mico E Social (cid:0) Bndes %TOTAL": "4,02", "Bb Gest\u00e3o de Recursos Dtvm S.A %ON": "1,06", "Bb Gest\u00e3o de Recursos Dtvm S.A %PN": "0,75", "Bb Gest\u00e3o de Recursos Dtvm S.A %TOTAL": "1,03", "Bndes Participa\u00e7\u00f5es S.A. - Bndespar %ON": "3,55", "Bndes Participa\u00e7\u00f5es S.A. - Bndespar %PN": "6,67", "Bndes Participa\u00e7\u00f5es S.A. - Bndespar %TOTAL": "3,93", "Caixa de Previd\u00eancia Dos Func. Do Banco Do Brasil %ON": "0,93", "Caixa de Previd\u00eancia Dos Func. Do Banco Do Brasil %PN": "0,37", "Caixa de Previd\u00eancia Dos Func. Do Banco Do Brasil %TOTAL": "0,86", "Caixa D.t.v.m. %ON": "1,88", "Caixa D.t.v.m. %PN": "0,07", "Caixa D.t.v.m. %TOTAL": "1,66", "Fundo de Investimento Caixa Fghab Multimercado %ON": "0,05", "Fundo de Investimento Caixa Fghab Multimercado %PN": "0,00", "Fundo de Investimento Caixa Fghab Multimercado %TOTAL": "0,04", "Fundo Nacional de Desenvolvimento - Fnd %ON": "2,25", "Fundo Nacional de Desenvolvimento - Fnd %PN": "0,00", "Fundo Nacional de Desenvolvimento - Fnd %TOTAL": "1,98", "Gera\u00e7\u00e3o Futuro L. Par Fia %ON": "0,07", "Gera\u00e7\u00e3o Futuro L. Par Fia %PN": "7,87", "Gera\u00e7\u00e3o Futuro L. Par Fia %TOTAL": "1,02", "Gic Private %ON": "6,40", "Gic Private %PN": "2,83", "Gic Private %TOTAL": "5,97", "Petros %ON": "0,24", "Petros %PN": "0,02", "Petros %TOTAL": "0,22", "Uni\u00e3o Federal %ON": "32,95", "Uni\u00e3o Federal %PN": "0,00", "Uni\u00e3o Federal %TOTAL": "28,95", "Vic Dtvm %ON": "0,01", "Vic Dtvm %PN": "0,13", "Vic Dtvm %TOTAL": "0,03", "Victor Adler %ON": "0,00", "Victor Adler %PN": "0,02", "Victor Adler %TOTAL": "0,00", "Outros %ON": "44,39", "Outros %PN": "61,50", "Outros %TOTAL": "46,47", "A\u00e7\u00f5es Tesouraria %ON": "2,46", "A\u00e7\u00f5es Tesouraria %PN": "2,44", "A\u00e7\u00f5es Tesouraria %TOTAL": "2,46"}, "A\u00e7\u00f5es em Circula\u00e7\u00e3o no Mercado": {"date": "27/04/2023", "csv": {"Pessoas F\u00edsicas - Quantidade": "134.891", "Pessoas F\u00edsicas - Percentual": "-", "Pessoas Jur\u00eddicas - Quantidade": "9.466", "Pessoas Jur\u00eddicas - Percentual": "-", "Investidores Institucionais - Quantidade": "1.390", "Investidores Institucionais - Percentual": "-", "Quantidade de A\u00e7\u00f5es Ordin\u00e1rias - Quantidade": "2.013.846.657", "Quantidade de A\u00e7\u00f5es Ordin\u00e1rias - Percentual": "99,35", "Quantidade de A\u00e7\u00f5es Preferenciais - Quantidade": "275.669.374", "Quantidade de A\u00e7\u00f5es Preferenciais - Percentual": "98,44", "Total de A\u00e7\u00f5es - Quantidade": "2.289.516.031", "Total de A\u00e7\u00f5es - Percentual": "99,24"}}, "Composi\u00e7\u00e3o do Capital Social": {"date": "05/01/2023", "csv": {"Ordin\u00e1rias": "2.027.011.498", "Preferenciais": "280.088.314", "Total": "2.307.099.812"}}}}